Workbook

Sheet Extraction_Log
A1: Extract_ID | B1: Source_Type | C1: Organisation | D1: Document_Title | E1: URL | F1: Year | G1: Geo_Scope | H1: Geo_Tier | I1: UK_Data | J1: Geo_Usage | K1: Verbatim_Extract | L1: Page_Section | M1: Word_Count | N1: Initial_Code_1 | O1: Initial_Code_2 | P1: Initial_Code_3 | Q1: Coding_Level | R1: Theme_Candidate | S1: Sub_Theme | T1: Framework_Alignment | U1: Confirmation_Status | V1: Cross_Reference | W1: Confidence_Level | X1: Notes | Y1: Date_Extracted | Z1: Reviewer_Decision | AA1: Exclusion_Note
A2: EXT_ALD_001 | B2: Retailer | C2: Aldi UK | D2: Aldi UK Sustainability Report 2024 | E2: https://dm.emea.cms.aldi.cx/is/content/aldiprodeu/AL01_Aldi_2024_SR_UK | F2: 2024 | G2: UK | H2: T1_UK_Specific | I2: Yes | J2: Primary_Evidence | K2: Our automated food waste report platform shows what is wasted in granular detail, so that we can see what's discarded most often. Then each store can target their food waste reduction actions accordingly | L2: p.26 (Tackling food waste) | M2: 33 | N2: automated_waste_reporting | O2: granular_data_analysis | P2: store_level_action | Q2: First_Order | R2: TH_01 | S2: Inventory_Accuracy | T2: TOE_Tech | U2: Verified | V2: None identified | W2: High | X2: Explicit mention of a technology platform used for 'granular' analysis to drive operational action. Directly addresses RQ1 (BD technologies) and RQ2 (waste reduction impact). | Y2: 07-01-2026 | Z2: Include
A3: EXT_ALD_002 | B3: Retailer | C3: Aldi UK | D3: Aldi UK Sustainability Report 2024 | E3: https://dm.emea.cms.aldi.cx/is/content/aldiprodeu/AL01_Aldi_2024_SR_UK | F3: 2024 | G3: UK | H3: T1_UK_Specific | I3: Yes | J3: Primary_Evidence | K3: Operationally, we have exceeded our short-term KPI to reduce operational food waste by 48%, by achieving a reduction of 72% by the end of 2024 (2017 baseline). | L3: p.26 (Tackling food waste) | M3: 29 | N3: operational_waste_reduction_72pct | O3: KPI_performance_exceeded | P3: 2017_baseline | Q3: First_Order | R3: TH_02 | S3: Food_Waste_Prevention | T3: 5Vs_Value | U3: Verified | V3: Cross-checks with EXT_ALD_009 (67% to 2023) | W3: High | X3: Quantifies the success of the operational strategies (including the platform mentioned in EXT_ALD_001). 72% reduction is a significant metric for RQ2. | Y3: 07-01-2026 | Z3: Include
A4: EXT_ALD_003 | B4: Retailer | C4: Aldi UK | D4: Aldi UK Sustainability Report 2024 | E4: https://dm.emea.cms.aldi.cx/is/content/aldiprodeu/AL01_Aldi_2024_SR_UK | F4: 2024 | G4: UK | H4: T1_UK_Specific | I4: Yes | J4: Primary_Evidence | K4: The shelf life for our core beef has increased from 8 to 15 days, reducing food waste. | L4: p.31 (Positive action on packaging) | M4: 19 | N4: shelf_life_extension_7days | O4: beef_inventory_optimisation | P4: packaging_innovation | Q4: First_Order | R4: TH_01 | S4: Stock_Availability | T4: SCOR_Make | U4: Verified | V4: None identified | W4: High | X4: Demonstrates inventory optimisation through product/packaging innovation. Extending shelf life directly impacts inventory holding capability and waste (RQ2). However, there is no relation with BD application, just packaging improvements. | Y4: 07-01-2026 | Z4: Exclude | AA4: Shelf life extension via packaging, not BD technology
A5: EXT_ALD_004 | B5: Retailer | C5: Aldi UK | D5: Aldi UK Sustainability Report 2024 | E5: https://dm.emea.cms.aldi.cx/is/content/aldiprodeu/AL01_Aldi_2024_SR_UK | F5: 2024 | G5: UK | H5: T1_UK_Specific | I5: Yes | J5: Primary_Evidence | K5: Our National Real Estate team has now installed 625 water Automatic Meter Reader devices in Aldi stores, and the project will be completed by the end of 2025. These devices mean we get quality water data | L5: p.19 (Managing water supplies) | M5: 36 | N5: IoT_meter_rollout_625_stores | O5: real_time_data_acquisition | P5: leak_detection | Q5: First_Order | R5: TH_04 | S5: Data_Infrastructure | T5: TOE_Tech | U5: Verified | V5: Cross-checks with EXT_ALD_010 (595 AMS) | W5: High | X5: Evidence of IoT adoption (Automatic Meter Readers). While water-focused, it proves the deployment of data-gathering infrastructure across the store estate (RQ1). | Y5: 07-01-2026 | Z5: Exclude | AA5: Water metering infrastructure - not related to inventory/BD
A6: EXT_ALD_005 | B6: Retailer | C6: Aldi UK | D6: Aldi UK Sustainability Report 2024 | E6: https://dm.emea.cms.aldi.cx/is/content/aldiprodeu/AL01_Aldi_2024_SR_UK | F6: 2024 | G6: UK | H6: T1_UK_Specific | I6: Yes | J6: Primary_Evidence | K6: To understand the difference we can make, we use supply chain data via 3Keel, who survey our suppliers... to calculate our annual soy footprint and monitor our performance. | L6: p.15 (Tackling deforestation) | M6: 28 | N6: 3Keel_supply_chain_analytics | O6: footprint_calculation_method | P6: supplier_data_survey | Q6: First_Order | R6: TH_04 | S6: Vendor_Partnerships | T6: SCOR_Source | U6: Verified | V6: Correlates with EXT_ALD_006 (D&A Services) | W6: High | X6: Example of using third-party data analytics (3Keel) for upstream supply chain visibility. Relevant to 'Source' phase of SCOR. Addresses RQ1 (BD technologies). | Y6: 07-01-2026 | Z6: Exclude | AA6: Soy footprint supplier monitoring - sustainability focus, not inventory
A7: EXT_ALD_006 | B7: Retailer | C7: Aldi Stores Limited | D7: Annual Report and Financial Statements 2024 | E7: https://find-and-update.company-information.service.gov.uk/company/02321869/filing-history | F7: 2024 | G7: UK | H7: T1_UK_Specific | I7: Yes | J7: Primary_Evidence | K7: During the year the group received services amounting to £19.775m (2023: £15.726m) from Aldi D&A Services GmbH. | L7: p.68, Note 25 (Related Party Transactions) | M7: 20 | N7: analytics_investment_£19.8m | O7: intragroup_services | P7: YoY_growth_26pct | Q7: First_Order | R7: TH_04 | S7: Centre_of_Excellence | T7: TOE_Org | U7: Verified | V7: Correlates with EXT_ALD_005 (3Keel partnership) | W7: High | X7: CRITICAL FINANCIAL EVIDENCE: Explicit quantifying of 'D&A' (Data & Analytics) spend. The 26% YoY increase (from £15.7m) proves accelerating investment in BD capabilities. Audited by KPMG. Supports RQ1 and RQ3. | Y7: 07-01-2026 | Z7: Include
A8: EXT_ALD_007 | B8: Retailer | C8: Aldi Stores Limited | D8: Annual Report and Financial Statements 2024 | E8: https://find-and-update.company-information.service.gov.uk/company/02321869/filing-history | F8: 2024 | G8: UK | H8: T1_UK_Specific | I8: Yes | J8: Primary_Evidence | K8: Aldi is rolling out Integrated Refrigeration Facility Management (IRFM), a middleware that automates work orders from alarms and supports predictive monitoring to optimise equipment performance. The system will be fully operational by the end of the year, enabling remote monitoring and lifecycle management of equipment | L8: p.17, Table 1 (Transition Risks) | M8: 44 | N8: predictive_monitoring_IRFM | O8: middleware_automation | P8: remote_lifecycle_management | Q8: First_Order | R8: TH_01 | S8: Inventory_Accuracy | T8: TOE_Tech | U8: Verified | V8: None identified | W8: High | X8: Specific naming of a 'middleware' technology (IRFM) used for 'predictive monitoring'. This is a key example of BD/IoT application in operational maintenance. Addresses RQ1. | Y8: 07-01-2026 | Z8: Exclude | AA8: BD applied to improve equipment performance. Not related to inventory optimisation.
A9: EXT_ALD_008 | B9: Retailer | C9: Aldi Stores Limited | D9: Annual Report and Financial Statements 2024 | E9: https://find-and-update.company-information.service.gov.uk/company/02321869/filing-history | F9: 2024 | G9: UK | H9: T1_UK_Specific | I9: Yes | J9: Primary_Evidence | K9: Net cash of £599m (2023: £597m) was used in investing activities, primarily reflecting the group's investment in its store and distribution network and technology infrastructure... Purchase of intangible assets 203K. | L9: p.4, Financial key performance indicators; p45, Cash flows from investing activities | M9: 27 | N9: tech_infrastructure_investment | O9: capex_£599m | P9: distribution_network | Q9: Mixed | R9: TH_04 | S9: Data_Infrastructure | T9: TOE_Org | U9: Verified | V9: None identified | W9: High | X9: Links 'technology infrastructure' directly to the primary capital expenditure figure (£599m). The 203K spent in intangible fixed assets suggests that tech is a top-level investment priority. Supports RQ3. | Y9: 07-01-2026 | Z9: Include
A10: EXT_ALD_009 | B10: Retailer | C10: Aldi Stores Limited | D10: Annual Report and Financial Statements 2024 | E10: https://find-and-update.company-information.service.gov.uk/company/02321869/filing-history | F10: 2024 | G10: UK | H10: T1_UK_Specific | I10: Yes | J10: Primary_Evidence | K10: Between 2017 and 2023, Aldi UK has reduced food waste intensity within its own operations by 67%. | L10: p.26, Waste Management | M10: 18 | N10: waste_intensity_reduction_67pct | O10: operational_efficiency | P10: 2017_baseline | Q10: First_Order | R10: TH_02 | S10: Food_Waste_Prevention | T10: SCOR_Return | U10: Verified | V10: Cross-checks with EXT_ALD_002 (72% to 2024) | W10: High | X10: Provides a hard longitudinal metric (67% reduction to 2023) for operational waste efficiency. Consistent with EXT_ALD_002 showing 72% by 2024. Directly relevant to RQ2. | Y10: 07-01-2026 | Z10: Exclude | AA10: Superseded by EXT_ALD_002 with updated 72% figure (end 2024)
A11: EXT_ALD_010 | B11: Retailer | C11: Aldi Stores Limited | D11: Annual Report and Financial Statements 2024 | E11: https://find-and-update.company-information.service.gov.uk/company/02321869/filing-history | F11: 2024 | G11: UK | H11: T1_UK_Specific | I11: Yes | J11: Primary_Evidence | K11: In FY2024, 595 AMS were installed at Aldi at sites... This system will create alerts when leaks or unusually high consumption have been identified to speed up leak detection. Its leak detection process resulted in engineers being dispatched to Aldi sites 43 times in 2024 | L11: p.26, Water Management | M11: 41 | N11: IoT_deployment_595_sites | O11: leak_detection_alerts | P11: automated_metering | Q11: First_Order | R11: TH_01 | S11: Supply_Chain_Visibility | T11: 5Vs_Velocity | U11: Cross_Check_Required | V11: Cross-checks with EXT_ALD_004 (625 AMR) | W11: High | X11: Confirms IoT rollout scale (595 AMS sites) and demonstrates 'velocity' value (speeding up leak detection). Note: discrepancy with EXT_ALD_004 (625 AMR) - terminology difference (AMS vs AMR) or different measurement periods. Addresses RQ1. | Y11: 07-01-2026 | Z11: Exclude | AA11: It relates to sustainability, not inventory optimisation or waste reduction.
A12: EXT_ASD_001 | B12: Retailer | C12: Asda (Bellis Finco PLC) | D12: Annual Report and Consolidated Financial Statements 2024 | E12: https://find-and-update.company-information.service.gov.uk/company/12855336/filing-history | F12: 2024 | G12: UK | H12: T1_UK_Specific | I12: Yes | J12: Primary_Evidence | K12: In Project Future we are delivering a best-in-class technology stack and unlocking breakthrough advancements in Food Retail data analytics. | L12: p.12 (Financial Review) | M12: 20 | N12: project_future_analytics | O12: breakthrough_advancements | P12: tech_stack_upgrade | Q12: First_Order | R12: TH_01 | S12: ROI_Metrics | T12: TOE_Tech | U12: Verified | V12: None identified | W12: High | X12: Direct evidence of BD/Analytics being a strategic priority ('breakthrough advancements'). Links 'Project Future' specifically to data capability upgrades. Addresses RQ1. | Y12: 07-01-2026 | Z12: Include
A13: EXT_ASD_002 | B13: Retailer | C13: Asda (Bellis Finco PLC) | D13: Annual Report and Consolidated Financial Statements 2024 | E13: https://find-and-update.company-information.service.gov.uk/company/12855336/filing-history | F13: 2024 | G13: UK | H13: T1_UK_Specific | I13: Yes | J13: Primary_Evidence | K13: Approaching the end of the programme, we have already delivered significant technology enhancements in all depots, home offices as well as rolling out inventory management solutions across over 800 stores, primarily our smaller formats. | L13: p.12 (Financial Review) | M13: 33 | N13: inventory_solutions_rollout_800_stores | O13: depot_tech_enhancement | P13: small_format_focus | Q13: First_Order | R13: TH_01 | S13: Inventory_Accuracy | T13: SCOR_Plan | U13: Verified | V13: Correlates with EXT_ASD_001 (Project Future) | W13: High | X13: Quantifies the scale of the technology rollout (800 stores). Explicitly links 'technology enhancements' to 'inventory management solutions', directly addressing RQ1. | Y13: 07-01-2026 | Z13: Include
A14: EXT_ASD_003 | B14: Retailer | C14: Asda (Bellis Finco PLC) | D14: Annual Report and Consolidated Financial Statements 2024 | E14: https://find-and-update.company-information.service.gov.uk/company/12855336/filing-history | F14: 2024 | G14: UK | H14: T1_UK_Specific | I14: Yes | J14: Primary_Evidence | K14: The separation programme is one-off and non-recurring in nature, and will transition the Group to a standalone, leading edge IT infrastructure using software as a service from best-in-class digital partners. Having no legacy systems will provide significant competitive advantage, deliver operating efficiencies, enable better use of data, and agility in taking on growth opportunities and in responding to customers' needs. Project Future is expected to complete in 2025. Cumulative cash outflow to 31 December 2024 for the project was £867m.Project Future is expected to complete in 2025. Cumulative cash outflow to 31 December 2024 for the project was £867m. | L14: p.22 (Reconciliation of IFRS to Non-IFRS Measures) | M14: 19 | N14: IT_transformation_cost_£867m | O14: cumulative_cash_outflow | P14: 2025_completion_target | Q14: First_Order | R14: TH_04 | S14: Data_Infrastructure | T14: TOE_Org | U14: Verified | V14: Cross-checks with Capital Expenditure section p.15 | W14: High | X14: CRITICAL: Provides the precise financial scale of IT/Data transformation (£867m cumulative). Massive 'sunk cost' investment to enable future BD capabilities. Addresses RQ3 (scaling challenges/opportunities). | Y14: 07-01-2026 | Z14: Include
A15: EXT_ASD_004 | B15: Retailer | C15: Asda (Bellis Finco PLC) | D15: Annual Report and Consolidated Financial Statements 2024 | E15: https://find-and-update.company-information.service.gov.uk/company/12855336/filing-history | F15: 2024 | G15: UK | H15: T1_UK_Specific | I15: Yes | J15: Primary_Evidence | K15: The provision for store inventory loss at 31 December 2024 is £87.1m (2023: £140.2m). | L15: p.100 (Notes to Financial Statements, Note 1) | M15: 16 | N15: inventory_loss_provision_£87.1m | O15: YoY_loss_reduction_38pct | P15: provision_accuracy | Q15: First_Order | R15: TH_02 | S15: Shrinkage_Reduction | T15: 5Vs_Veracity | U15: Verified | V15: Potentially linked to EXT_ASD_002 (inventory solutions) | W15: High | X15: CRITICAL METRIC: Hard financial data on 'inventory loss' (shrinkage). Significant reduction from £140.2m to £87.1m (~38% reduction) suggests improved control/accuracy, potentially linked to new systems. Addresses RQ2. | Y15: 07-01-2026 | Z15: Include
A16: EXT_ASD_005 | B16: Retailer | C16: Asda (Bellis Finco PLC) | D16: Annual Report and Consolidated Financial Statements 2024 | E16: https://find-and-update.company-information.service.gov.uk/company/12855336/filing-history | F16: 2024 | G16: UK | H16: T1_UK_Specific | I16: Yes | J16: Primary_Evidence | K16: Disciplined execution and supply management minimised clearance markdown and maximised full price sales, improving margins and lowering inventory through the year. | L16: p.14 (Financial Review - Non-food) | M16: 21 | N16: inventory_reduction_outcome | O16: markdown_minimisation | P16: margin_improvement | Q16: Mixed | R16: TH_02 | S16: Markdown_Optimisation | T16: SCOR_Deliver | U16: Verified | V16: None identified | W16: High | X16: Qualitative evidence of the impact of 'supply management' (inventory control) on financial outcomes (margin, markdown). Connects inventory levels to profitability. Addresses RQ2. | Y16: 07-01-2026 | Z16: Include
A17: EXT_ASD_006 | B17: Retailer | C17: Asda (Bellis Finco PLC) | D17: Environmental, Social & Governance (ESG) Report 2024 | E17: https://asdagroceries.scene7.com/is/content/asdagroceries/Z%20FUTURE/Microsites/Corporate/Documents/ESG_Report_2024.pdf | F17: 2025 | G17: UK | H17: T1_UK_Specific | I17: Yes | J17: Primary_Evidence | K17: Asda, along with other UK supermarkets, in collaboration with the Leeds Institute of Data Analytics (LIDA) at the University of Leeds, is assessing the impact of these location-based restrictions on consumer behaviour | L17: p.6 (Healthy and Sustainable Choices) | M17: 33 | N17: LIDA_data_analytics_collaboration | O17: consumer_behaviour_assessment | P17: location_based_restrictions | Q17: First_Order | R17: TH_04 | S17: Vendor_Partnerships | T17: TOE_Env | U17: Verified | V17: None identified | W17: High | X17: Evidence of academic partnership for high-level data analytics (Leeds Institute of Data Analytics). Demonstrates use of external expertise to leverage Big Data for strategic insights. Addresses RQ1. | Y17: 07-01-2026 | Z17: Exclude | AA17: It relates to assessing customer behaviour towards unhealthy High Fat, Sugar, and Salt (HFSS) items
A18: EXT_ASD_007 | B18: Retailer | C18: Asda (Bellis Finco PLC) | D18: Environmental, Social & Governance (ESG) Report 2024 | E18: https://asdagroceries.scene7.com/is/content/asdagroceries/Z%20FUTURE/Microsites/Corporate/Documents/ESG_Report_2024.pdf | F18: 2025 | G18: UK | H18: T1_UK_Specific | I18: Yes | J18: Primary_Evidence | K18: The new packaging enables the shelf life of the product to be increased by up to 9 days, reducing waste and keeping the product fresher for longer. | L18: p.7 (Sustainable Choices) | M18: 25 | N18: shelf_life_extension_9days | O18: waste_reduction_mechanism | P18: packaging_innovation | Q18: First_Order | R18: TH_01 | S18: Stock_Availability | T18: SCOR_Make | U18: Verified | V18: Compare with EXT_ALD_003 (Aldi beef 7 days) | W18: High | X18: Shows how physical product/packaging innovation directly alters inventory parameters (shelf life), which feeds into BD algorithms for ordering/stock holding. Addresses RQ2. Compare with Aldi's 7-day extension. | Y18: 07-01-2026 | Z18: Exclude | AA18: It relats to product packaging
A19: EXT_ASD_008 | B19: Retailer | C19: Asda (Bellis Finco PLC) | D19: Environmental, Social & Governance (ESG) Report 2024 | E19: https://asdagroceries.scene7.com/is/content/asdagroceries/Z%20FUTURE/Microsites/Corporate/Documents/ESG_Report_2024.pdf | F19: 2025 | G19: UK | H19: T1_UK_Specific | I19: Yes | J19: Primary_Evidence | K19: In December 2024, Asda launched a trial with Land App... The goal is to explore how remote sensing technology can support farmers to improve soil health, reduce risks like flooding, and enhance wildlife habitats. | L19: p.10 (Nature - Land App trial) | M19: 34 | N19: remote_sensing_technology | O19: land_app_trial | P19: supply_chain_visibility | Q19: First_Order | R19: TH_04 | S19: Data_Infrastructure | T19: TOE_Tech | U19: Verified | V19: None identified | W19: High | X19: Specific mention of 'remote sensing technology' and mapping apps in upstream supply chain. Clear SCOR_Source phase data application for risk reduction. Extends data visibility to farm level. Addresses RQ1. | Y19: 07-01-2026 | Z19: Exclude | AA19: The technology mentioned relates to extended risk reduction on farms
A20: EXT_ASD_009 | B20: Retailer | C20: Asda (Bellis Finco PLC) | D20: Environmental, Social & Governance (ESG) Report 2024 | E20: https://asdagroceries.scene7.com/is/content/asdagroceries/Z%20FUTURE/Microsites/Corporate/Documents/ESG_Report_2024.pdf | F20: 2025 | G20: UK | H20: T1_UK_Specific | I20: Yes | J20: Primary_Evidence | K20: Our 2024 data shows a reduction in food waste of 15.1% YOY and 7% against our baseline. | L20: p.41 (Scorecards - Zero Waste) | M20: 19 | N20: food_waste_reduction_15.1pct | O20: YoY_performance | P20: 2024_data | Q20: First_Order | R20: TH_02 | S20: Food_Waste_Prevention | T20: SCOR_Return | U20: Verified | V20: Cross-checks with Zero Waste section p.12 | W20: High | X20: Quantified success metric (15.1% YoY reduction) resulting from 'reduction, redistribution and repurposing' strategies managed via data/inventory systems. Compare with Aldi's 72% long-term reduction. Addresses RQ2. | Y20: 07-01-2026 | Z20: Include | AA20: Page number corrected from 21 to 41
A21: EXT_ASD_010 | B21: Retailer | C21: Asda (Bellis Finco PLC) | D21: Environmental, Social & Governance (ESG) Report 2024 | E21: https://asdagroceries.scene7.com/is/content/asdagroceries/Z%20FUTURE/Microsites/Corporate/Documents/ESG_Report_2024.pdf | F21: 2025 | G21: UK | H21: T1_UK_Specific | I21: Yes | J21: Primary_Evidence | K21: Enhanced data quality has also enabled more accurate tracking and analysis of health performance across the portfolio. | L21: p.21 (Scorecards - Healthy Choices) | M21: 17 | N21: enhanced_data_quality | O21: accurate_tracking_analysis | P21: portfolio_performance | Q21: First_Order | R21: TH_04 | S21: Data_Infrastructure | T21: 5Vs_Veracity | U21: Verified | V21: None identified | W21: High | X21: Explicit acknowledgment that 'enhanced data quality' is a prerequisite for accurate analysis. Directly supports 'Veracity' aspect of 5Vs framework. Identifies data quality as an enabler. Addresses RQ3. | Y21: 07-01-2026 | Z21: Exclude | AA21: It relates to the business’s overall Health Score, the nutritional profile of products sold
A22: EXT_ICE_001 | B22: Retailer | C22: Iceland Foods Limited | D22: Financial Statements for the 52 week period ended 28 March 2025 | E22: https://find-and-update.company-information.service.gov.uk/company/01107406/filing-history | F22: 2025 | G22: UK | H22: T1_UK_Specific | I22: Yes | J22: Primary_Evidence | K22: The new Warehouse Management system has been successfully rolled out to all of our Regional Distribution Centres with the final implementation completed as planned in July 2025... using technology to support this. | L22: p.7 (Supply chain) | M22: 30 | N22: WMS_rollout_completed | O22: supply_chain_productivity | P22: RDC_technology | Q22: First_Order | R22: TH_01 | S22: Supply_Chain_Visibility | T22: TOE_Tech | U22: Verified | V22: None identified | W22: High | X22: Confirms completion of major technology infrastructure project (WMS) across all RDCs. Critical evidence for Legacy Systems being updated to modern tech. Addresses RQ1. | Y22: 07-01-2026 | Z22: Include
A23: EXT_ICE_002 | B23: Retailer | C23: Iceland Foods Limited | D23: Financial Statements for the 52 week period ended 28 March 2025 | E23: https://find-and-update.company-information.service.gov.uk/company/01107406/filing-history | F23: 2025 | G23: UK | H23: T1_UK_Specific | I23: Yes | J23: Primary_Evidence | K23: We are also introducing technology that will allow us to boost sales and reduce waste by making dynamic markdowns of products nearing the end of their shelf life. | L23: p.11 (Outlook) | M23: 25 | N23: dynamic_markdown_technology | O23: waste_reduction | P23: shelf_life_management | Q23: First_Order | R23: TH_02 | S23: Markdown_Optimisation | T23: SCOR_Return | U23: Verified | V23: Correlates with EXT_ICE_006 (Gander technology) | W23: High | X23: Explicit mention of 'dynamic markdown' technology. Specific BD/AI application for inventory clearance and waste minimisation. Addresses RQ2. | Y23: 07-01-2026 | Z23: Include
A24: EXT_ICE_003 | B24: Retailer | C24: Iceland Foods Limited | D24: Financial Statements for the 52 week period ended 28 March 2025 | E24: https://find-and-update.company-information.service.gov.uk/company/01107406/filing-history | F24: 2025 | G24: UK | H24: T1_UK_Specific | I24: Yes | J24: Primary_Evidence | K24: Our FY25 Food Waste report... showed that we had achieved a 38% reduction in food and drink waste since our baseline in FY18, and a 12% reduction from FY24. | L24: p.10 (Environmental, Social & Governance) | M24: 29 | N24: waste_reduction_38pct | O24: YoY_reduction_12pct | P24: FY25_metrics | Q24: First_Order | R24: TH_02 | S24: Food_Waste_Prevention | T24: SCOR_Return | U24: Verified | V24: Cross-checks with EXT_ICE_008 (Sustainability Report) | W24: High | X24: Hard quantification of waste reduction (38% vs FY18 baseline, 12% YoY). Validates effectiveness of inventory management and supply chain strategies. Addresses RQ2. | Y24: 07-01-2026 | Z24: Include
A25: EXT_ICE_004 | B25: Retailer | C25: Iceland Foods Limited | D25: Financial Statements for the 52 week period ended 28 March 2025 | E25: https://find-and-update.company-information.service.gov.uk/company/01107406/filing-history | F25: 2025 | G25: UK | H25: T1_UK_Specific | I25: Yes | J25: Primary_Evidence | K25: This new technology, and an increased focus on our customer insight function, has driven better than ever retention of our online customers. | L25: p.6 (Online) | M25: 20 | N25: customer_insight_focus | O25: technology_driven_retention | P25: online_performance | Q25: Mixed | R25: TH_01 | S25: Demand_Forecasting | T25: 5Vs_Value | U25: Verified | V25: None identified | W25: High | X25: Links 'technology' and 'customer insight' directly to retention metrics. Shows the 'Value' (5Vs) derived from data analytics in the online channel. Addresses RQ1. | Y25: 07-01-2026 | Z25: Include
A26: EXT_ICE_005 | B26: Retailer | C26: Iceland Foods Limited | D26: Financial Statements for the 52 week period ended 28 March 2025 | E26: https://find-and-update.company-information.service.gov.uk/company/01107406/filing-history | F26: 2025 | G26: UK | H26: T1_UK_Specific | I26: Yes | J26: Primary_Evidence | K26: Amazon customers are over 90% incremental to Iceland Online and are opening the business to a larger customer base. | L26: p.6 (Online) | M26: 18 | N26: incremental_data_90pct | O26: new_channel_analytics | P26: amazon_partnership | Q26: First_Order | R26: TH_05 | S26: Online_Competition | T26: 5Vs_Volume | U26: Verified | V26: None identified | W26: High | X26: Data-driven insight into customer segmentation. '90% incremental' proves use of data to validate channel strategy and demand sources. Addresses RQ3 (scaling opportunities). | Y26: 07-01-2026 | Z26: Include
A27: EXT_ICE_006 | B27: Retailer | C27: Iceland Foods Limited | D27: Annual Sustainability Report 2024-2025 | E27: https://sustainability.iceland.co.uk/wp-content/uploads/2025/11/24-25-ESG-Report.pdf | F27: 2025 | G27: UK | H27: T1_UK_Specific | I27: Yes | J27: Primary_Evidence | K27: Gander's technology allows customers to browse reduced items at nearby stores in real time... We trialled both of these programmes in 24/25 and saw hugely positive results. Therefore, they will be rolled out nationally in 25/26. | L27: p.17 (Food Waste Reduction Workstreams) | M27: 36 | N27: real_time_markdown_visibility | O27: Gander_app_integration | P27: national_rollout_25/26 | Q27: First_Order | R27: TH_02 | S27: Markdown_Optimisation | T27: TOE_Tech | U27: Verified | V27: Correlates with EXT_ICE_002 (dynamic markdowns) | W27: High | X27: Explicitly identifies 'Gander's technology' as enabler for real-time inventory visibility to customers. Connects Stock Availability with Markdown Optimisation. National rollout 25/26. Addresses RQ1 & RQ2. | Y27: 07-01-2026 | Z27: Include
A28: EXT_ICE_007 | B28: Retailer | C28: Iceland Foods Limited | D28: Annual Sustainability Report 2024-2025 | E28: https://sustainability.iceland.co.uk/wp-content/uploads/2025/11/24-25-ESG-Report.pdf | F28: 2025 | G28: UK | H28: T1_UK_Specific | I28: Yes | J28: Primary_Evidence | K28: To tackle our overall carbon emissions, in 2024 we introduced 'Green Mile', which is a dedicated project to reduce our scope 3 emissions by optimising load efficiency... This is a data driven project | L28: p.13 (Carbon Workstreams - Green Mile) | M28: 32 | N28: Green_Mile_project | O28: data_driven_logistics | P28: load_efficiency_optimisation | Q28: First_Order | R28: TH_02 | S28: Transport_Efficiency | T28: SCOR_Deliver | U28: Verified | V28: None identified | W28: High | X28: Identifies specific 'data driven project' (Green Mile) for logistics optimisation. Demonstrates BD use for Transport Efficiency within SCOR Deliver phase. Secondary carbon benefit noted but primary focus is load efficiency. Addresses RQ1. | Y28: 07-01-2026 | Z28: Include
A29: EXT_ICE_008 | B29: Retailer | C29: Iceland Foods Limited | D29: Annual Sustainability Report 2024-2025 | E29: https://sustainability.iceland.co.uk/wp-content/uploads/2025/11/24-25-ESG-Report.pdf | F29: 2025 | G29: UK | H29: T1_UK_Specific | I29: Yes | J29: Primary_Evidence | K29: 0.48% represents a 38% decrease in food surplus produced from our baseline year 2017/18 and a 12% reduction from our previous financial year. | L29: p.16 (Food Waste Reduction) | M29: 23 | N29: food_waste_reduction_38pct | O29: YoY_reduction_12pct | P29: operational_surplus_metric | Q29: First_Order | R29: TH_02 | S29: Food_Waste_Prevention | T29: SCOR_Return | U29: Verified | V29: Cross-checks with EXT_ICE_003 (Financial Statements) | W29: High | X29: Provides precise impact metrics (38% reduction vs 2017/18 baseline). Validates the 'Value' (5Vs) of data initiatives. Consistent with Financial Statement figure. Addresses RQ2. | Y29: 07-01-2026 | Z29: Include
A30: EXT_ICE_009 | B30: Retailer | C30: Iceland Foods Limited | D30: Annual Sustainability Report 2024-2025 | E30: https://sustainability.iceland.co.uk/wp-content/uploads/2025/11/24-25-ESG-Report.pdf | F30: 2025 | G30: UK | H30: T1_UK_Specific | I30: Yes | J30: Primary_Evidence | K30: In 2024 work started with edenseven to enhance our emissions reporting and management through their digital carbon platform, cero.earth... generate insights to support strategic decision-making. | L30: p.10 (Carbon - Overview) | M30: 24 | N30: digital_carbon_platform | O30: cero_earth_implementation | P30: strategic_insight_generation | Q30: First_Order | R30: TH_04 | S30: Data_Infrastructure | T30: TOE_Tech | U30: Verified | V30: None identified | W30: High | X30: Names specific digital platform (cero.earth) for 'strategic decision-making'. Highlights infrastructure investment required to manage data. While carbon-focused, demonstrates broader data platform adoption. Addresses RQ3. | Y30: 07-01-2026 | Z30: Exclude | AA30: Carbon emissions platform - sustainability reporting, not inventory
A31: EXT_ICE_010 | B31: Retailer | C31: Iceland Foods Limited | D31: Annual Sustainability Report 2024-2025 | E31: https://sustainability.iceland.co.uk/wp-content/uploads/2025/11/24-25-ESG-Report.pdf | F31: 2025 | G31: UK | H31: T1_UK_Specific | I31: Yes | J31: Primary_Evidence | K31: The Move to -15°C is a sustainability initiative dedicated to cutting carbon emissions in the frozen food supply chain... This requires deep collaboration across both industry and academia, which the coalition aims to enable by encouraging knowledge sharing | L31: p.13 (Partnership with Minus 15 Coalition) | M31: 36 | N31: frozen_supply_chain_temp_shift | O31: industry_academia_collaboration | P31: emission_reduction_initiative | Q31: Second_Order | R31: TH_04 | S31: Vendor_Partnerships | T31: TOE_Env | U31: Verified | V31: None identified | W31: High | X31: Highlights need for 'knowledge sharing' and 'collaboration' (TOE Environment) to change supply chain parameters. Impacts inventory storage/energy costs. Iceland-specific as frozen food specialist. Addresses RQ3. | Y31: 07-01-2026 | Z31: Exclude | AA31: Frozen food carbon initiative - sustainability, not inventory optimisation
A32: EXT_LID_001 | B32: Retailer | C32: Lidl Great Britain Limited | D32: Annual Report and Financial Statements 2025 | E32: https://find-and-update.company-information.service.gov.uk/company/02816429/filing-history | F32: 2025 | G32: UK | H32: T1_UK_Specific | I32: Yes | J32: Primary_Evidence | K32: 60% of our stores now have energy data from sub-metered service entry units reporting live, every 15 minutes into our national platform... outputs from the system are provided to regions regularly to support improved analysis. | L32: p.25 (Directors' Report - Energy) | M32: 33 | N32: energy_management_platform | O32: live_data_reporting_15min | P32: sub_metering_60pct_coverage | Q32: First_Order | R32: TH_04 | S32: Data_Infrastructure | T32: 5Vs_Velocity | U32: Verified | V32: None identified | W32: High | X32: Excellent example of 'Velocity' in Big Data: live streams of energy data every 15 minutes. 60% coverage indicates implementation in progress but significant scale. Addresses RQ1. | Y32: 08-01-2026 | Z32: Exclude | AA32: Energy sub-metering - sustainability infrastructure, not inventory
A33: EXT_LID_002 | B33: Retailer | C33: Lidl Great Britain Limited | D33: Annual Report and Financial Statements 2025 | E33: https://find-and-update.company-information.service.gov.uk/company/02816429/filing-history | F33: 2025 | G33: UK | H33: T1_UK_Specific | I33: Yes | J33: Primary_Evidence | K33: The Company also continues to issue weekly offers through its rewards app, Lidl Plus, which has now hit more than 11 million users in UK. | L33: p.4 (Strategic Report - Key Business Achievements) | M33: 25 | N33: Lidl_Plus_11m_users | O33: digital_rewards_app | P33: customer_engagement_scale | Q33: First_Order | R33: TH_01 | S33: Omnichannel_Integration | T33: 5Vs_Volume | U33: Verified | V33: None identified | W33: High | X33: Quantifies the 'Volume' of customer data available (11 million users). This app is a primary source for demand forecasting data and personalised inventory marketing. Addresses RQ1. | Y33: 08-01-2026 | Z33: Include
A34: EXT_LID_003 | B34: Retailer | C34: Lidl Great Britain Limited | D34: Annual Report and Financial Statements 2025 | E34: https://find-and-update.company-information.service.gov.uk/company/02816429/filing-history | F34: 2025 | G34: UK | H34: T1_UK_Specific | I34: Yes | J34: Primary_Evidence | K34: An initiative which was introduced to help achieve these targets is an electronic labelling system. This is estimated to save over 206 tonnes of carbon annually through paper and packaging reductions | L34: p.21 (Corporate Governance - Protecting the planet) | M34: 31 | N34: electronic_labelling_system | O34: ESL_implementation | P34: process_digitisation | Q34: First_Order | R34: TH_04 | S34: Data_Infrastructure | T34: TOE_Tech | U34: Verified | V34: None identified | W34: High | X34: Explicit mention of Electronic Shelf Labels (ESL). While framed as sustainability initiative, ESL is critical inventory pricing technology enabling dynamic markdown and real-time price updates. Secondary carbon benefit noted. Addresses RQ1. | Y34: 08-01-2026 | Z34: Include
A35: EXT_LID_004 | B35: Retailer | C35: Lidl Great Britain Limited | D35: Annual Report and Financial Statements 2025 | E35: https://find-and-update.company-information.service.gov.uk/company/02816429/filing-history | F35: 2025 | G35: UK | H35: T1_UK_Specific | I35: Yes | J35: Primary_Evidence | K35: Progress (FY2025) 33% [against target] By 2030, we will have reduced Lidl GB's food waste by 50% (relative) | L35: p.16 (Strategic Report - Performance) | M35: 19 | N35: food_waste_reduction_33pct | O35: 2030_target_progress | P35: relative_reduction | Q35: First_Order | R35: TH_02 | S35: Food_Waste_Prevention | T35: SCOR_Return | U35: Verified | V35: Cross-checks with Zero Waste narrative p.21 | W35: High | X35: Hard metric on waste reduction (33% progress toward 50% target), validating effectiveness of inventory control measures. Addresses RQ2. | Y35: 08-01-2026 | Z35: Include
A36: EXT_LID_005 | B36: Retailer | C36: Lidl Great Britain Limited | D36: Annual Report and Financial Statements 2025 | E36: https://find-and-update.company-information.service.gov.uk/company/02816429/filing-history | F36: 2025 | G36: UK | H36: T1_UK_Specific | I36: Yes | J36: Primary_Evidence | K36: Construction taking place during the period on its Belvedere distribution centre to double its capacity, along with the completion of the expansion of its Bridgend distribution centre. | L36: p.4 (Strategic Report - Enhancing presence) | M36: 26 | N36: RDC_capacity_doubling | O36: warehouse_infrastructure | P36: network_expansion | Q36: First_Order | R36: TH_04 | S36: Scalable_Architecture | T36: SCOR_Deliver | U36: Verified | V36: None identified | W36: High | X36: Physical infrastructure expansion ('doubling capacity') is prerequisite for scaling BD-driven supply chain operations. Supports SCOR Deliver phase analysis. Addresses RQ3. | Y36: 08-01-2026 | Z36: Include
A37: EXT_LID_006 | B37: Retailer | C37: Lidl Great Britain Limited | D37: The Lidl Effect: Lidl GB's socioeconomic impact FY24 | E37: https://corporate.lidl.co.uk/content/download/148017/file/Lidl%20GB%20The%20Lidl%20Effect%20SER%20FY24.pdf | F37: 2025 | G37: UK | H37: T1_UK_Specific | I37: Yes | J37: Primary_Evidence | K37: In 2024 alone, we donated 18.5 million meals through a combination of food surplus and customer donations, while continuing to invest in educational programmes | L37: p.2 (Introduction) | M37: 24 | N37: surplus_donation_18.5m_meals | O37: food_waste_diversion | P37: community_investment | Q37: First_Order | R37: TH_02 | S37: Food_Waste_Prevention | T37: SCOR_Return | U37: Verified | V37: Validated by EXT_LID_009 (Assurance Statement) | W37: High | X37: Quantifies the output of inventory management 'return' processes (donation vs waste). The 18.5m meals figure is a key outcome of inventory surplus management system. Addresses RQ2. | Y37: 08-01-2026 | Z37: Include
A38: EXT_LID_007 | B38: Retailer | C38: Lidl Great Britain Limited | D38: The Lidl Effect: Lidl GB's socioeconomic impact FY24 | E38: https://corporate.lidl.co.uk/content/download/148017/file/Lidl%20GB%20The%20Lidl%20Effect%20SER%20FY24.pdf | F38: 2025 | G38: UK | H38: T1_UK_Specific | I38: Yes | J38: Primary_Evidence | K38: British suppliers, who already supply around two-thirds of the products we sell. | L38: p.2 (Introduction) | M38: 13 | N38: British_sourcing_2/3rds | O38: supplier_localisation | P38: inventory_sourcing_strategy | Q38: First_Order | R38: TH_01 | S38: Supply_Chain_Visibility | T38: SCOR_Source | U38: Verified | V38: None identified | W38: High | X38: Sourcing 2/3rds from local suppliers impacts inventory velocity (shorter lead times) and risk. Relevant to SCOR Source and Plan phases. Addresses RQ1. | Y38: 08-01-2026 | Z38: Include
A39: EXT_LID_008 | B39: Retailer | C39: Lidl Great Britain Limited | D39: The Lidl Effect: Lidl GB's socioeconomic impact FY24 | E39: https://corporate.lidl.co.uk/content/download/148017/file/Lidl%20GB%20The%20Lidl%20Effect%20SER%20FY24.pdf | F39: 2025 | G39: UK | H39: T1_UK_Specific | I39: Yes | J39: Primary_Evidence | K39: The store's contribution will further add to the £14.5 billion in Gross Value Added (GVA) Lidl generated for the GB economy in 2024. | L39: p.2 (Introduction) | M39: 23 | N39: GVA_contribution_£14.5bn | O39: economic_impact_scale | P39: market_value_creation | Q39: First_Order | R39: TH_05 | S39: Market_Concentration | T39: 5Vs_Value | U39: Verified | V39: None identified | W39: High | X39: Shows scale of operation (£14.5bn GVA). Establishes Volume and Value context for Big Data implementation. Addresses RQ3 (scaling context). | Y39: 08-01-2026 | Z39: Include
A40: EXT_LID_009 | B40: Consultancy | C40: Forvis Mazars LLP | D40: Independent Limited Assurance Report to the Directors of Lidl Great Britain Limited | E40: https://corporate.lidl.co.uk/pdf/show/148017 | F40: 2025 | G40: UK | H40: T1_UK_Specific | I40: Yes | J40: Supporting_Evidence | K40: We have conducted a limited assurance engagement on the Subject Matter Information... disclosed in the Socio-Economic Impact Report FY24 | L40: p.1 (Assurance Statement) | M40: 19 | N40: independent_assurance_verification | O40: data_reliability_check | P40: FY24_reporting | Q40: Second_Order | R40: TH_04 | S40: Data_Infrastructure | T40: 5Vs_Veracity | U40: Verified | V40: Confirms EXT_LID_006 | W40: High | X40: Independent auditor verification of non-financial metrics (including meal donations). Increases reliability/Veracity of data extracted in EXT_LID_006. Addresses RQ3 (data governance). | Y40: 08-01-2026 | Z40: Include
A41: EXT_LID_010 | B41: Retailer | C41: Lidl Great Britain Limited | D41: The Lidl Effect: Lidl GB's socioeconomic impact FY24 | E41: https://corporate.lidl.co.uk/content/download/148017/file/Lidl%20GB%20The%20Lidl%20Effect%20SER%20FY24.pdf | F41: 2025 | G41: UK | H41: T1_UK_Specific | I41: Yes | J41: Primary_Evidence | K41: Supplier classification may also create uncertainty, as sector codes do not always capture the full scope of a supplier's activities. | L41: p.27 (Methodology - Limitations) | M41: 19 | N41: data_classification_uncertainty | O41: supplier_coding_limitations | P41: modelling_constraints | Q41: Second_Order | R41: TH_03 | S41: Data_Quality_Issues | T41: 5Vs_Veracity | U41: Verified | V41: None identified | W41: High | X41: CRITICAL: Explicit admission of data limitations regarding supplier classification codes. Direct evidence of Data Quality Issues (Veracity) acting as barrier to perfect analytics. Addresses RQ3 (challenges). | Y41: 08-01-2026 | Z41: Include
A42: EXT_LID_011 | B42: Retailer | C42: Lidl Great Britain Limited | D42: Lidl GB Sustainability Report FY23/24: Beyond the Basket | E42: https://corporate.lidl.co.uk/content/download/146615/file/Lidl%20GB%20FY%202023-2024%20Beyond%20the%20basket%20report.pdf | F42: 2025 | G42: UK | H42: T1_UK_Specific | I42: Yes | J42: Primary_Evidence | K42: Since 2024, we have worked with Mondra and M2030, data reporting platforms, to carbon-footprint our products, track supplier emissions helping us to identify and take action on emissions hotspots within our supply chain | L42: p.19 (Future-ready supply chains) | M42: 33 | N42: data_platforms_Mondra_M2030 | O42: carbon_footprinting_analytics | P42: emission_hotspot_action | Q42: First_Order | R42: TH_04 | S42: Vendor_Partnerships | T42: TOE_Tech | U42: Verified | V42: None identified | W42: High | X42: Explicit naming of specific data platforms (Mondra, M2030) used for supply chain analytics. Demonstrates Technology aspect of TOE and move towards data-driven decision making. While carbon-focused, shows broader platform adoption pattern. Addresses RQ1. | Y42: 08-01-2026 | Z42: Exclude | AA42: Carbon footprinting products/supplier emissions - sustainability, not inventory
A43: EXT_LID_012 | B43: Retailer | C43: Lidl Great Britain Limited | D43: Lidl GB Sustainability Report FY23/24: Beyond the Basket | E43: https://corporate.lidl.co.uk/content/download/146615/file/Lidl%20GB%20FY%202023-2024%20Beyond%20the%20basket%20report.pdf | F43: 2025 | G43: UK | H43: T1_UK_Specific | I43: Yes | J43: Primary_Evidence | K43: We have built a database of more than 7,000 individual supply chain sites that grow our food. Understanding where our food is coming from is key to identifying location-specific risks | L43: p.29 (Biodiversity) | M43: 32 | N43: supply_chain_database_7000_sites | O43: location_specific_risk_ID | P43: upstream_visibility | Q43: First_Order | R43: TH_01 | S43: Supply_Chain_Visibility | T43: 5Vs_Volume | U43: Verified | V43: None identified | W43: High | X43: Quantifies scale of data collection (7,000 sites), directly addressing 'Volume' aspect of Big Data. This database enables granular risk management. Compare with Asda's 3Keel supplier data. Addresses RQ1. | Y43: 08-01-2026 | Z43: Include
A44: EXT_LID_013 | B44: Retailer | C44: Lidl Great Britain Limited | D44: Lidl GB Sustainability Report FY23/24: Beyond the Basket | E44: https://corporate.lidl.co.uk/content/download/146615/file/Lidl%20GB%20FY%202023-2024%20Beyond%20the%20basket%20report.pdf | F44: 2025 | G44: UK | H44: T1_UK_Specific | I44: Yes | J44: Primary_Evidence | K44: Our vacuum-packed beef mince packaging... reduces plastic use by a remarkable 63%... And it even doubles the shelf life of the mince and halves food waste while in store. | L44: p.25 (Packaging) | M44: 30 | N44: shelf_life_doubled | O44: food_waste_halved | P44: vacuum_packaging_innovation | Q44: First_Order | R44: TH_01 | S44: Stock_Availability | T44: SCOR_Make | U44: Verified | V44: Compare with EXT_ALD_003 (Aldi 7 days), EXT_ASD_007 (Asda 9 days) | W44: High | X44: Technological innovation in packaging that directly alters inventory parameters (doubling shelf life, halving waste). Massive impact on inventory holding capacity. Compare with Aldi (7 days) and Asda (9 days) shelf life extensions. Addresses RQ2. | Y44: 08-01-2026 | Z44: Include
A45: EXT_LID_014 | B45: Retailer | C45: Lidl Great Britain Limited | D45: Lidl GB Sustainability Report FY23/24: Beyond the Basket | E45: https://corporate.lidl.co.uk/content/download/146615/file/Lidl%20GB%20FY%202023-2024%20Beyond%20the%20basket%20report.pdf | F45: 2025 | G45: UK | H45: T1_UK_Specific | I45: Yes | J45: Primary_Evidence | K45: In 2023, we launched a national donation KPI to track the proportion of unsold food that we send to good causes. Since we introduced it, we have increased our donation tonnage by over 300%. | L45: p.26 (Food too good to waste) | M45: 33 | N45: donation_KPI_300pct_increase | O45: unsold_food_tracking | P45: waste_redistribution_efficiency | Q45: First_Order | R45: TH_02 | S45: Food_Waste_Prevention | T45: 5Vs_Value | U45: Verified | V45: Cross-checks with EXT_LID_006 (18.5m meals) | W45: High | X45: Demonstrates power of 'Value' (5Vs) derived from simple data metrics (KPIs). The act of measuring and tracking drove 300% operational improvement. Direct evidence that data-driven management improves outcomes. Addresses RQ2. | Y45: 08-01-2026 | Z45: Include
A46: EXT_LID_015 | B46: Retailer | C46: Lidl Great Britain Limited | D46: Lidl GB Sustainability Report FY23/24: Beyond the Basket | E46: https://corporate.lidl.co.uk/content/download/146615/file/Lidl%20GB%20FY%202023-2024%20Beyond%20the%20basket%20report.pdf | F46: 2025 | G46: UK | H46: T1_UK_Specific | I46: Yes | J46: Primary_Evidence | K46: In 2024, we introduced a new open-book costing model, which brings transparency to the costs of production while also assuring minimum volumes and a fixed margin for our pork farmers. | L46: p.42 (Backing British) | M46: 29 | N46: open_book_costing_model | O46: cost_transparency | P46: guaranteed_volumes | Q46: First_Order | R46: TH_04 | S46: Vendor_Partnerships | T46: SCOR_Source | U46: Verified | V46: None identified | W46: High | X46: 'Open-book' implies data sharing between retailer and supplier. This transparency is key enabler for Big Data integration in SCOR Source phase. Addresses RQ3 (scaling enablers). | Y46: 08-01-2026 | Z46: Include
A47: EXT_MKS_001 | B47: Retailer | C47: Marks and Spencer Group plc | D47: Annual Report and Financial Statements 2025 | E47: https://corporate.marksandspencer.com/sites/marksandspencer/files/2025-05/Marks-and-Spencer-Group-plc-Annual-Report-and-Financial-Statements-2025_INTERACTIVE_FINAL.pdf | F47: 2025 | G47: UK | H47: T1_UK_Specific | I47: Yes | J47: Primary_Evidence | K47: The roll out of the new forecasting and ordering system was completed. This helps to better match supply to variable demand... The 'One Best Way' retail operations programme is helping to improve productivity, reducing stock file errors and making the new forecasting system more effective. | L47: p.15 (Strategic Progress - Food) | M47: 41 | N47: forecasting_ordering_system_rollout | O47: supply_demand_matching | P47: stock_file_error_reduction | Q47: First_Order | R47: TH_01 | S47: Demand_Forecasting | T47: SCOR_Plan | U47: Verified | V47: None identified | W47: High | X47: Direct confirmation of BD technology implementation ('forecasting and ordering system'). Explicitly links technology to 'variable demand' matching and 'stock file' accuracy. Addresses RQ1. | Y47: 08-01-2026 | Z47: Include
A48: EXT_MKS_002 | B48: Retailer | C48: Marks and Spencer Group plc | D48: Annual Report and Financial Statements 2025 | E48: https://corporate.marksandspencer.com/sites/marksandspencer/files/2025-05/Marks-and-Spencer-Group-plc-Annual-Report-and-Financial-Statements-2025_INTERACTIVE_FINAL.pdf | F48: 2025 | G48: UK | H48: T1_UK_Specific | I48: Yes | J48: Primary_Evidence | K48: There is so much in our two main businesses that still requires investment and change: legacy systems, a supply chain in both Food and Fashion, Home & Beauty which is well below industry leading standards and in some cases inefficient | L48: p.5 (Chairman's Letter) | M48: 37 | N48: legacy_systems_inefficiency | O48: supply_chain_below_standard | P48: investment_requirement | Q48: First_Order | R48: TH_03 | S48: Legacy_Systems | T48: TOE_Tech | U48: Verified | V48: None identified | W48: High | X48: CRITICAL: Chairman's admission regarding 'legacy systems' being 'well below industry leading standards'. Strong evidence for Adoption Barriers (RQ3), validating need for digital transformation. Rare senior-level acknowledgment. | Y48: 08-01-2026 | Z48: Include
A49: EXT_MKS_003 | B49: Retailer | C49: Marks and Spencer Group plc | D49: Annual Report and Financial Statements 2025 | E49: https://corporate.marksandspencer.com/sites/marksandspencer/files/2025-05/Marks-and-Spencer-Group-plc-Annual-Report-and-Financial-Statements-2025_INTERACTIVE_FINAL.pdf | F49: 2025 | G49: UK | H49: T1_UK_Specific | I49: Yes | J49: Primary_Evidence | K49: The acquisition of Gist has also delivered improved logistics service and a contribution of more than £60m to profit which provides the foundations for a long-term investment to modernise the network and create efficient capacity for growth. | L49: p.13 (Strategic Progress - Delivering target operating margins) | M49: 36 | N49: logistics_profit_contribution_£60m | O49: Gist_acquisition_impact | P49: modernisation_foundation | Q49: First_Order | R49: TH_04 | S49: Data_Infrastructure | T49: TOE_Org | U49: Verified | V49: Cross-checks with financial review p.23 | W49: High | X49: Quantifies financial impact (£60m profit) of vertical integration (Gist acquisition). Structural change enables data-driven modernisation. Addresses RQ3 (scaling enablers). | Y49: 08-01-2026 | Z49: Include
A50: EXT_MKS_004 | B50: Retailer | C50: Marks and Spencer Group plc | D50: Annual Report and Financial Statements 2025 | E50: https://corporate.marksandspencer.com/sites/marksandspencer/files/2025-05/Marks-and-Spencer-Group-plc-Annual-Report-and-Financial-Statements-2025_INTERACTIVE_FINAL.pdf | F50: 2025 | G50: UK | H50: T1_UK_Specific | I50: Yes | J50: Primary_Evidence | K50: This includes migration to the Ocado Smart Platform (OSP) solution across e-commerce, last-mile, supply chain, customer hub and trading systems... improving delivery efficiency and maximising capacity utilisation | L50: p.21 (Ocado Retail) | M50: 26 | N50: Ocado_Smart_Platform_migration | O50: supply_chain_digitisation | P50: capacity_utilisation | Q50: First_Order | R50: TH_01 | S50: Omnichannel_Integration | T50: TOE_Tech | U50: Verified | V50: Cross-checks with Ocado Retail section | W50: High | X50: Identifies specific BD/AI technology ('Ocado Smart Platform') for end-to-end supply chain visibility and efficiency. OSP is industry-leading automated fulfilment technology. Addresses RQ1 and RQ3. | Y50: 08-01-2026 | Z50: Include
A51: EXT_MKS_005 | B51: Retailer | C51: Marks and Spencer Group plc | D51: Annual Report and Financial Statements 2025 | E51: https://corporate.marksandspencer.com/sites/marksandspencer/files/2025-05/Marks-and-Spencer-Group-plc-Annual-Report-and-Financial-Statements-2025_INTERACTIVE_FINAL.pdf | F51: 2025 | G51: UK | H51: T1_UK_Specific | I51: Yes | J51: Primary_Evidence | K51: This year, we donated the equivalent of 30m meals in surplus food through our partnership with Neighbourly, reaching the milestone of donating the equivalent of 100m meals over the last decade. | L51: p.7 (Our Markets - More Sustainable Choices) | M51: 30 | N51: surplus_donation_30m_meals | O51: waste_redistribution_partnership | P51: Neighbourly_collaboration | Q51: First_Order | R51: TH_02 | S51: Food_Waste_Prevention | T51: SCOR_Return | U51: Verified | V51: Cross-checks with ESG section p.37 | W51: High | X51: Quantifies SCOR Return phase outcome. Data-driven surplus identification enabled 30m meals donation (100m cumulative). Compare with Lidl's 18.5m meals. Addresses RQ2. | Y51: 08-01-2026 | Z51: Include
A52: EXT_MKS_006 | B52: Retailer | C52: Marks and Spencer Group plc | D52: ESG Report 2025 | E52: https://corporate.marksandspencer.com/sites/marksandspencer/files/2025-05/Marks-and-Spencer-Group-plc-ESG-Report-2025.pdf | F52: 2025 | G52: UK | H52: T1_UK_Specific | I52: Yes | J52: Primary_Evidence | K52: This year, we have completed the onboarding of suppliers representing 96% of our MMCF volume on to Textile Genesis. Not only does this platform give us visibility of our supply chain, but it also allows us to strengthen our compliance checks | L52: p.22 (Fashion, Home & Beauty - Traceability) | M52: 38 | N52: Textile_Genesis_96pct_coverage | O52: supply_chain_visibility_platform | P52: compliance_strengthening | Q52: First_Order | R52: TH_01 | S52: Supply_Chain_Visibility | T52: TOE_Tech | U52: Verified | V52: None identified | W52: High | X52: Explicit naming of 'Textile Genesis' platform for traceability. High coverage (96%) indicates maturity in upstream data gathering. While Fashion-focused, demonstrates BD platform adoption pattern applicable to Food. Addresses RQ1. | Y52: 08-01-2026 | Z52: Exclude | AA52: Textile Genesis MMCF traceability - clothing sustainability, not food inventory
A53: EXT_MKS_007 | B53: Retailer | C53: Marks and Spencer Group plc | D53: ESG Report 2025 | E53: https://corporate.marksandspencer.com/sites/marksandspencer/files/2025-05/Marks-and-Spencer-Group-plc-ESG-Report-2025.pdf | F53: 2025 | G53: UK | H53: T1_UK_Specific | I53: Yes | J53: Primary_Evidence | K53: In 2023/24 we successfully modelled the carbon footprint of over 5,000 M&S products across the Foodhall... This takes us to almost 6,000 products on the platform. | L53: p.23 (Food - Making our products with care) | M53: 26 | N53: product_footprint_modelling_6000_SKUs | O53: Mondra_platform_analytics | P53: secondary_to_primary_data | Q53: First_Order | R53: TH_04 | S53: Data_Infrastructure | T53: 5Vs_Variety | U53: Verified | V53: Compare with Lidl Mondra/M2030 usage (EXT_LID_011) | W53: High | X53: Quantifies data volume (6,000 products) processed via Mondra analytics platform. Note: Lidl also uses Mondra (EXT_LID_011). Demonstrates BD use for granular product-level analysis. Addresses RQ1. | Y53: 08-01-2026 | Z53: Exclude | AA53: Carbon footprint modelling products - sustainability, not inventory
A54: EXT_MKS_008 | B54: Retailer | C54: Marks and Spencer Group plc | D54: ESG Report 2025 | E54: https://corporate.marksandspencer.com/sites/marksandspencer/files/2025-05/Marks-and-Spencer-Group-plc-ESG-Report-2025.pdf | F54: 2025 | G54: UK | H54: T1_UK_Specific | I54: Yes | J54: Primary_Evidence | K54: In September 2024 we updated our in-store process to make our food redistribution data even more robust. While it was rolled out, the changeover resulted in a drop in data accuracy... from 85% to 80% | L54: p.26 (Food - Wasting as little as possible) | M54: 32 | N54: data_accuracy_drop_5pct | O54: process_update_impact | P54: redistribution_data_robustness | Q54: First_Order | R54: TH_03 | S54: Data_Quality_Issues | T54: 5Vs_Veracity | U54: Verified | V54: Compare with EXT_LID_010 (data classification uncertainty) | W54: High | X54: CRITICAL: Rare explicit admission of 'drop in data accuracy' (85%→80%) caused by process update. Direct evidence of Data Quality Issues (Veracity) as barrier. Compare with Lidl's data classification admission. Addresses RQ3. | Y54: 08-01-2026 | Z54: Include
A55: EXT_MKS_009 | B55: Retailer | C55: Marks and Spencer Group plc | D55: ESG Report 2025 | E55: https://corporate.marksandspencer.com/sites/marksandspencer/files/2025-05/Marks-and-Spencer-Group-plc-ESG-Report-2025.pdf | F55: 2025 | G55: UK | H55: T1_UK_Specific | I55: Yes | J55: Primary_Evidence | K55: With our supplier partner Huntapac, we tested the impact of automation... This included a robot for seed bed forming and a self-driving tractor... the analysis showed an average fuel saving of 47% versus conventional methods. | L55: p.20 (Food - Lower-impact farming) | M55: 31 | N55: automation_fuel_saving_47pct | O55: robotics_trial_Huntapac | P55: self_driving_tractor | Q55: First_Order | R55: TH_01 | S55: Labour_Optimisation | T55: TOE_Tech | U55: Verified | V55: None identified | W55: High | X55: Specific robotics/automation example (self-driving tractor) delivering hard efficiency metrics (47% fuel saving). Demonstrates BD-enabled precision agriculture in UK food supply chain. Addresses RQ1 and RQ2. | Y55: 08-01-2026 | Z55: Exclude | AA55: Agricultural automation/fuel savings - farming operations, not retail inventory
A56: EXT_MKS_010 | B56: Retailer | C56: Marks and Spencer Group plc | D56: ESG Report 2025 | E56: https://corporate.marksandspencer.com/sites/marksandspencer/files/2025-05/Marks-and-Spencer-Group-plc-ESG-Report-2025.pdf | F56: 2025 | G56: UK | H56: T1_UK_Specific | I56: Yes | J56: Primary_Evidence | K56: Through Manufacture 2030... This includes over 200 partners which cover over 50% of our food supplier emissions... [we] have seen... a 26% increase in suppliers adopting Scope 1, 2 and 3 targets. | L56: p.23 (Food - Making our products with care) | M56: 30 | N56: supplier_data_platform_200_partners | O56: Manufacture_2030_engagement | P56: scope_3_target_adoption | Q56: First_Order | R56: TH_04 | S56: Vendor_Partnerships | T56: SCOR_Source | U56: Verified | V56: None identified | W56: High | X56: Shows scale of data integration with suppliers (200 partners, 50% emissions coverage). Manufacture 2030 platform enables Scope 3 data flow. Addresses RQ3 (scaling enablers via partnerships). | Y56: 08-01-2026 | Z56: Exclude | AA56: Manufacture 2030 supplier emissions - sustainability platform, not inventory
A57: EXT_MOR_001 | B57: Retailer | C57: Wm Morrison Supermarkets Limited | D57: Annual Report and Financial Statements for the 52 weeks ended 27 October 2024 | E57: https://www.morrisons-corporate.com/globalassets/corporatesite/investor-centre/financialreports/documents/2023-24/wm-morrison-supermarkets-limited-2024-28-01-25.pdf | F57: 2025 | G57: UK | H57: T1_UK_Specific | I57: Yes | J57: Primary_Evidence | K57: Availability has improved significantly during the year, with our customer satisfaction scores improving by 9% year-on-year. | L57: p.6 (Financial results) | M57: 18 | N57: availability_improvement_9pct | O57: customer_satisfaction_score | P57: YoY_improvement | Q57: First_Order | R57: TH_01 | S57: Stock_Availability | T57: 5Vs_Value | U57: Verified | V57: None identified | W57: High | X57: Links 'availability' (inventory outcome) directly to customer satisfaction metrics. 9% improvement suggests effective inventory management interventions. Addresses RQ1 and RQ2. | Y57: 08-01-2026 | Z57: Include
A58: EXT_MOR_002 | B58: Retailer | C58: Wm Morrison Supermarkets Limited | D58: Annual Report and Financial Statements for the 52 weeks ended 27 October 2024 | E58: https://www.morrisons-corporate.com/globalassets/corporatesite/investor-centre/financialreports/documents/2023-24/wm-morrison-supermarkets-limited-2024-28-01-25.pdf | F58: 2025 | G58: UK | H58: T1_UK_Specific | I58: Yes | J58: Primary_Evidence | K58: We have continued to leverage our loyalty scheme, the More Card, with swipe rates increasing to over 50% of transactions... allowing us to offer more personalised value to our customers. | L58: p.11 (Customers) | M58: 26 | N58: More_Card_swipe_rate_50pct | O58: loyalty_scheme_adoption | P58: personalised_value_data | Q58: First_Order | R58: TH_05 | S58: Technology_Differentiation | T58: 5Vs_Volume | U58: Verified | V58: Compare with Lidl Plus 11m users (EXT_LID_002) | W58: High | X58: High swipe rate (50%) indicates massive Volume of customer data being generated. Raw material for 'personalised value' (BD Analytics). Compare with Lidl Plus. Addresses RQ1. | Y58: 08-01-2026 | Z58: Include
A59: EXT_MOR_003 | B59: Retailer | C59: Wm Morrison Supermarkets Limited | D59: Annual Report and Financial Statements for the 52 weeks ended 27 October 2024 | E59: https://www.morrisons-corporate.com/globalassets/corporatesite/investor-centre/financialreports/documents/2023-24/wm-morrison-supermarkets-limited-2024-28-01-25.pdf | F59: 2025 | G59: UK | H59: T1_UK_Specific | I59: Yes | J59: Primary_Evidence | K59: In 2024, we reduced our operational food waste by 13% compared to the previous year, saving over 4,000 tonnes of food from going to waste. | L59: p.24 (Environment - Waste) | M59: 23 | N59: operational_waste_reduction_13pct | O59: waste_savings_4000_tonnes | P59: metric_tonnage_reduction | Q59: First_Order | R59: TH_02 | S59: Food_Waste_Prevention | T59: SCOR_Return | U59: Verified | V59: Cross-checks with ESG section; compare Aldi 72%, Iceland 38% | W59: High | X59: Hard metric on waste efficiency (13% reduction, 4,000 tonnes). Demonstrates Value of operational controls and inventory management. Addresses RQ2. | Y59: 08-01-2026 | Z59: Include
A60: EXT_MOR_004 | B60: Retailer | C60: Wm Morrison Supermarkets Limited | D60: Annual Report and Financial Statements for the 52 weeks ended 27 October 2024 | E60: https://www.morrisons-corporate.com/globalassets/corporatesite/investor-centre/financialreports/documents/2023-24/wm-morrison-supermarkets-limited-2024-28-01-25.pdf | F60: 2025 | G60: UK | H60: T1_UK_Specific | I60: Yes | J60: Primary_Evidence | K60: Our vertically integrated supply chain model, 'Market Street', allows us to control the quality and freshness of over 50% of the fresh food we sell, giving us a unique advantage in managing inventory flow. | L60: p.4 (Business Model) | M60: 31 | N60: vertical_integration_50pct_control | O60: inventory_flow_management | P60: Market_Street_model | Q60: First_Order | R60: TH_01 | S60: Supply_Chain_Visibility | T60: SCOR_Make | U60: Verified | V60: None identified | W60: High | X60: Highlights Morrisons' unique vertical integration (SCOR Make phase). Controlling 50% of fresh food allows tighter inventory control and swifter data reaction. Unique structural advantage. Addresses RQ1. | Y60: 08-01-2026 | Z60: Include
A61: EXT_MOR_005 | B61: Retailer | C61: Wm Morrison Supermarkets Limited | D61: Annual Report and Financial Statements for the 52 weeks ended 27 October 2024 | E61: https://www.morrisons-corporate.com/globalassets/corporatesite/investor-centre/financialreports/documents/2023-24/wm-morrison-supermarkets-limited-2024-28-01-25.pdf | F61: 2025 | G61: UK | H61: T1_UK_Specific | I61: Yes | J61: Primary_Evidence | K61: We continue to invest in our technology infrastructure to improve efficiency and cyber security resilience... Capital expenditure for the year was £453m, reflecting investment in our store estate and technology. | L61: p.9 (Financial Key Performance Indicators) | M61: 24 | N61: capex_tech_investment_£453m | O61: infrastructure_efficiency | P61: resilience_investment | Q61: Mixed | R61: TH_04 | S61: Data_Infrastructure | T61: TOE_Tech | U61: Verified | V61: Cross-checks with Cash Flow Statement | W61: High | X61: Aggregated figure for Tech/Store investment (£453m). While broad, confirms significant capital allocation towards 'technology infrastructure' as enabler. Addresses RQ3. | Y61: 08-01-2026 | Z61: Include
A62: EXT_MOR_006 | B62: Retailer | C62: Wm Morrison Supermarkets Limited | D62: Morrisons Sustainability Report 2023/2024 | E62: https://www.morrisons-corporate.com/globalassets/corporatesite/sustainability/morrisons_sustainability_report_22_23_final.pdf | F62: 2025 | G62: UK | H62: T1_UK_Specific | I62: Yes | J62: Primary_Evidence | K62: used the data from Manufacture 2030 to feed into our revised Scope 3 model for the first time, ensuring accurate primary data is used. During FY23/24 over 200 suppliers reported data to us utilising M2030. | L62: p.12 (Carbon emissions in our supply chain) | M62: 35 | N62: Manufacture_2030_platform | O62: primary_data_accuracy | P62: supplier_reporting_200_sites | Q62: First_Order | R62: TH_04 | S62: Vendor_Partnerships | T62: SCOR_Source | U62: Verified | V62: Compare M&S M2030 usage (EXT_MKS_010), Lidl M2030 (EXT_LID_011) | W62: High | X62: Highlights transition from secondary to primary data using M2030 platform. Third retailer using M2030 (after M&S and Lidl). 200 suppliers reporting. Addresses RQ1 and RQ3. | Y62: 08-01-2026 | Z62: Exclude | AA62: Manufacture 2030 Scope 3 reporting - sustainability, not inventory
A63: EXT_MOR_007 | B63: Retailer | C63: Wm Morrison Supermarkets Limited | D63: Morrisons Sustainability Report 2023/2024 | E63: https://www.morrisons-corporate.com/globalassets/corporatesite/sustainability/morrisons_sustainability_report_22_23_final.pdf | F63: 2025 | G63: UK | H63: T1_UK_Specific | I63: Yes | J63: Primary_Evidence | K63: In 2024 over 800 tonnes of food nearing the end of it's life was sold via Too Good To Go... saved more than 2 million Surprise bags since the beginning of our partnership in 2019 | L63: p.15 (Food Waste - Too Good To Go) | M63: 34 | N63: Too_Good_To_Go_sales_800t | O63: waste_redistribution_2m_bags | P63: partnership_expansion_930_stores | Q63: First_Order | R63: TH_02 | S63: Food_Waste_Prevention | T63: SCOR_Return | U63: Verified | V63: Cross-checks with EXT_MOR_003 (13% waste reduction) | W63: High | X63: Quantifies success of consumer-facing app (Too Good To Go) in reducing inventory waste. 800 tonnes sold (not wasted) is direct efficiency gain. 2m bags cumulative. Addresses RQ2. | Y63: 08-01-2026 | Z63: Include
A64: EXT_MOR_008 | B64: Retailer | C64: Wm Morrison Supermarkets Limited | D64: Morrisons Sustainability Report 2023/2024 | E64: https://www.morrisons-corporate.com/globalassets/corporatesite/sustainability/morrisons_sustainability_report_22_23_final.pdf | F64: 2025 | G64: UK | H64: T1_UK_Specific | I64: Yes | J64: Primary_Evidence | K64: We have continued to work with Map of Ag, building up several years worth of farm baseline emissions data. Baseline emissions footprinting is still being rolled out | L64: p.12 (Net zero agriculture) | M64: 26 | N64: Map_of_Ag_data_collection | O64: farm_baseline_emissions | P64: longitudinal_data | Q64: First_Order | R64: TH_04 | S64: Data_Infrastructure | T64: SCOR_Source | U64: Verified | V64: Compare Asda Land App trial (EXT_ASD_008) | W64: High | X64: Identifies 'Map of Ag' as key data partner for farm-level visibility. 'Building up several years' indicates Volume/History aspect of Big Data being created. Compare with Asda's Land App. Addresses RQ1. | Y64: 08-01-2026 | Z64: Exclude | AA64: Map of Ag farm emissions - agricultural sustainability, not inventory
A65: EXT_MOR_009 | B65: Retailer | C65: Wm Morrison Supermarkets Limited | D65: Morrisons Sustainability Report 2023/2024 | E65: https://www.morrisons-corporate.com/globalassets/corporatesite/sustainability/morrisons_sustainability_report_22_23_final.pdf | F65: 2025 | G65: UK | H65: T1_UK_Specific | I65: Yes | J65: Primary_Evidence | K65: Within FY23/24 our Scope 1 emissions increased by circa 7.2%... We also have improved data accuracy, capturing data that was previously estimated. | L65: p.11 (Energy efficiency in our own operations) | M65: 21 | N65: data_accuracy_impact_7.2pct | O65: estimated_vs_actual_capture | P65: emissions_reporting_integrity | Q65: First_Order | R65: TH_03 | S65: Data_Quality_Issues | T65: 5Vs_Veracity | U65: Verified | V65: Compare M&S accuracy drop (EXT_MKS_008), Lidl data uncertainty (EXT_LID_010) | W65: High | X65: CRITICAL: Clear example of Veracity issues - improved data capture led to reported INCREASE in emissions (7.2%). Demonstrates 'J-curve' of data adoption where visibility initially worsens reported metrics. Key evidence for RQ3 challenges. | Y65: 08-01-2026 | Z65: Exclude | AA65: Scope 1 emissions reporting - sustainability accounting, not inventory
A66: EXT_MOR_010 | B66: Retailer | C66: Wm Morrison Supermarkets Limited | D66: Morrisons Sustainability Report 2023/2024 | E66: https://www.morrisons-corporate.com/globalassets/corporatesite/sustainability/morrisons_sustainability_report_22_23_final.pdf | F66: 2025 | G66: UK | H66: T1_UK_Specific | I66: Yes | J66: Primary_Evidence | K66: We internally monitor our water usage across all operations and use this data to identify any high consumption to alert our manufacturing sites to early identification of leaks... In FY23/24 we used 4,616,978 m³ of water... a 6% reduction | L66: p.16 (Operational Water Usage) | M66: 38 | N66: water_usage_monitoring_data | O66: leak_detection_alerts | P66: consumption_reduction_6pct | Q66: First_Order | R66: TH_01 | S66: Inventory_Accuracy | T66: 5Vs_Velocity | U66: Verified | V66: Compare Aldi AMR devices (EXT_ALD_004, EXT_ALD_010) | W66: High | X66: Demonstrates real-time (Velocity) data usage for operational efficiency ('early identification of leaks'). Direct link between data monitoring and resource reduction (6%). Compare with Aldi's AMR rollout. Addresses RQ1 and RQ2. | Y66: 08-01-2026 | Z66: Exclude | AA66: Water usage monitoring - sustainability, not inventory
A67: EXT_OCA_001 | B67: Retailer | C67: Ocado Retail Limited | D67: Annual Report and Financial Statements 2025 | E67: https://ocadoretail.com/wp-content/uploads/2025/09/OCADO-ANNUAL-REPORT_2025.pdf | F67: 2025 | G67: UK | H67: T1_UK_Specific | I67: Yes | J67: Primary_Evidence | K67: For the 12 month period to 1 December 2024, food waste represented 0.49% of food handled (0.43% for 12-month period to 3 December in 2023). This is a 17% reduction against Ocado Retail's baseline (0.59% in 2022) | L67: p.30 (Environment) | M67: 16 | N67: food_waste_0.49pct | O67: industry_leading_low | P67: YoY_increase_0.1pct | Q67: First_Order | R67: TH_02 | S67: Food_Waste_Prevention | T67: SCOR_Return | U67: Verified | V67: Cross-checks with EXT_OCA_006 (0.49%) | W67: High | X67: CRITICAL: Exceptionally low waste figure (0.49%) validates efficiency of centralised, data-driven inventory model. Industry-leading benchmark. Compare with traditional retailers (Aldi 72% reduction, not absolute). Addresses RQ2. | Y67: 08-01-2026 | Z67: Include | AA67: Corrected page number from 22 to 30
A68: EXT_OCA_002 | B68: Retailer | C68: Ocado Retail Limited | D68: Annual Report and Financial Statements 2025 | E68: https://ocadoretail.com/wp-content/uploads/2025/09/OCADO-ANNUAL-REPORT_2025.pdf | F68: 2025 | G68: UK | H68: T1_UK_Specific | I68: Yes | J68: Primary_Evidence | K68: Perfect Execution is our programme to improve our customer proposition... improving availability and freshness, and reducing substitutions... Substitutions have reduced by 30% year-on-year. | L68: p.4 (Strategic Report - Perfect Execution) | M68: 24 | N68: substitutions_reduction_30pct | O68: availability_freshness_improvement | P68: Perfect_Execution_programme | Q68: First_Order | R68: TH_01 | S68: Stock_Availability | T68: SCOR_Deliver | U68: Verified | V68: None identified | W68: High | X68: Direct evidence of inventory accuracy improvement. 30% drop in substitutions implies significantly better demand forecasting and real-time stock visibility. Key BD application. Addresses RQ1 and RQ2. | Y68: 08-01-2026 | Z68: Include
A69: EXT_OCA_003 | B69: Retailer | C69: Ocado Retail Limited | D69: Annual Report and Financial Statements 2025 | E69: https://ocadoretail.com/wp-content/uploads/2025/09/OCADO-ANNUAL-REPORT_2025.pdf | F69: 2025 | G69: UK | H69: T1_UK_Specific | I69: Yes | J69: Primary_Evidence | K69: Active customers have grown by 12.3% to 1.07 million... driven by our 'Big Price Drop' and improved service. | L69: p.6 (Key Performance Indicators) | M69: 19 | N69: active_customers_1.07m | O69: customer_growth_12.3pct | P69: big_price_drop_impact | Q69: First_Order | R69: TH_05 | S69: Market_Concentration | T69: 5Vs_Volume | U69: Verified | V69: Cross-checks with Financial Review p.7 | W69: High | X69: Quantifies Volume of customer base (1.07m). Growth increases data pool for predictive analytics, reinforcing BD feedback loop. Compare with Lidl Plus 11m (different model). Addresses RQ1. | Y69: 08-01-2026 | Z69: Include
A70: EXT_OCA_004 | B70: Retailer | C70: Ocado Retail Limited | D70: Annual Report and Financial Statements 2025 | E70: https://ocadoretail.com/wp-content/uploads/2025/09/OCADO-ANNUAL-REPORT_2025.pdf | F70: 2025 | G70: UK | H70: T1_UK_Specific | I70: Yes | J70: Primary_Evidence | K70: The migration of our Bristol CFC to the Ocado Smart Platform (OSP) was completed in the period. This provides us with the latest generation of robotic fulfilment technology. | L70: p.8 (Financial Review - Operations) | M70: 26 | N70: OSP_migration_Bristol | O70: robotic_fulfilment | P70: latest_generation_tech | Q70: First_Order | R70: TH_01 | S70: ROI_Metrics | T70: TOE_Tech | U70: Verified | V70: Compare M&S OSP migration (EXT_MKS_004) | W70: High | X70: Explicit mention of 'Ocado Smart Platform' (OSP) and 'robotic fulfilment'. Core technological enabler (TOE) for inventory management. Note: M&S also uses OSP. Addresses RQ1 and RQ3. | Y70: 08-01-2026 | Z70: Include
A71: EXT_OCA_005 | B71: Retailer | C71: Ocado Retail Limited | D71: Annual Report and Financial Statements 2025 | E71: https://ocadoretail.com/wp-content/uploads/2025/09/OCADO-ANNUAL-REPORT_2025.pdf | F71: 2025 | G71: UK | H71: T1_UK_Specific | I71: Yes | J71: Primary_Evidence | K71: We have leveraged the 'Ocado Price Promise', which matches the price of like-for-like products... This is supported by our sophisticated data matching technology. | L71: p.5 (Ocado Retail at a Glance) | M71: 28 | N71: algorithmic_price_matching | O71: Ocado_Price_Promise | P71: data_matching_tech | Q71: First_Order | R71: TH_05 | S71: Technology_Differentiation | T71: 5Vs_Value | U71: Verified | V71: None identified | W71: High | X71: 'Sophisticated data matching technology' explicitly cited as enabler for pricing strategy. Demonstrates Value generation through competitor data analysis. Addresses RQ1. | Y71: 08-01-2026 | Z71: Include
A72: EXT_OCA_006 | B72: Retailer | C72: Ocado Retail Limited | D72: Sustainability Report for the 70 weeks ended 6 April 2025 | E72: https://sustainability.ocadoretail.com/wp-content/uploads/2025/09/Ocado-Sustainability-Report-2024-2025.pdf | F72: 2025 | G72: UK | H72: T1_UK_Specific | I72: Yes | J72: Primary_Evidence | K72: Reduce food waste in our own operations... 0.49% (2024 FY) [vs] 0.59% (2022) | L72: p.52 (Our governance and reporting - Food waste) | M72: 14 | N72: food_waste_0.49pct | O72: baseline_comparison_0.59pct | P72: operational_efficiency | Q72: First_Order | R72: TH_01 | S72: Inventory_Accuracy | T72: SCOR_Return | U72: Verified | V72: Cross-checks with EXT_OCA_001 (0.5%) | W72: High | X72: Precise metric (0.49%) confirms high inventory accuracy. Shows improvement from 0.59% baseline (2022). Cross-validates Annual Report figure. Industry-leading performance. Addresses RQ2. | Y72: 08-01-2026 | Z72: Include
A73: EXT_OCA_007 | B73: Retailer | C73: Ocado Retail Limited | D73: Sustainability Report for the 70 weeks ended 6 April 2025 | E73: https://sustainability.ocadoretail.com/wp-content/uploads/2025/09/Ocado-Sustainability-Report-2024-2025.pdf | F73: 2025 | G73: UK | H73: T1_UK_Specific | I73: Yes | J73: Primary_Evidence | K73: Eliminate unnecessary packaging, minimise material use... Total tonnage removed... 44.5 tonnes [in 2024 FY] | L73: p.52 (Our governance and reporting - Responsible packaging) | M73: 16 | N73: packaging_reduction_44.5t | O73: material_use_minimisation | P73: tonnage_removed_metric | Q73: First_Order | R73: TH_02 | S73: Transport_Efficiency | T73: SCOR_Make | U73: Verified | V73: None identified | W73: High | X73: Quantifies physical reduction of packaging (44.5t). Links Make phase efficiency to reduced material handling costs. Secondary environmental benefit noted. Addresses RQ2. | Y73: 08-01-2026 | Z73: Exclude | AA73: Packaging tonnage reduction - sustainability, not inventory optimisation
A74: EXT_OCA_008 | B74: Retailer | C74: Ocado Retail Limited | D74: Sustainability Report for the 70 weeks ended 6 April 2025 | E74: https://sustainability.ocadoretail.com/wp-content/uploads/2025/09/Ocado-Sustainability-Report-2024-2025.pdf | F74: 2025 | G74: UK | H74: T1_UK_Specific | I74: Yes | J74: Primary_Evidence | K74: Working together: Powering innovation and collaborations that drive systemic change... Our online reusable packaging scheme | L74: p.2 (Contents - Innovation) | M74: 17 | N74: reusable_packaging_scheme | O74: online_reuse_system | P74: systemic_change_innovation | Q74: First_Order | R74: TH_04 | S74: Data_Infrastructure | T74: SCOR_Return | U74: Verified | V74: None identified | W74: High | X74: 'Online reusable packaging scheme' implies BD application for asset tracking/reverse logistics. Innovation in Return phase requiring data systems. Addresses RQ1. | Y74: 08-01-2026 | Z74: Exclude | AA74: Reusable packaging scheme - sustainability initiative, not inventory
A75: EXT_OCA_009 | B75: Retailer | C75: Ocado Retail Limited | D75: Sustainability Report for the 70 weeks ended 6 April 2025 | E75: https://sustainability.ocadoretail.com/wp-content/uploads/2025/09/Ocado-Sustainability-Report-2024-2025.pdf | F75: 2025 | G75: UK | H75: T1_UK_Specific | I75: Yes | J75: Primary_Evidence | K75: From farm to freezer with The Felix Project | L75: p.2 (Contents - Communities) | M75: 8 | N75: Felix_Project_partnership | O75: farm_to_freezer_initiative | P75: surplus_redistribution | Q75: First_Order | R75: TH_04 | S75: Vendor_Partnerships | T75: SCOR_Return | U75: Verified | V75: Compare M&S Neighbourly (EXT_MKS_005), Morrisons Too Good To Go (EXT_MOR_007) | W75: High | X75: Specific partnership (Felix Project) and supply chain initiative (Farm to freezer) to manage surplus. Different redistribution model to M&S/Morrisons. Addresses RQ3. | Y75: 08-01-2026 | Z75: Include
A76: EXT_OCA_010 | B76: Retailer | C76: Ocado Retail Limited | D76: Sustainability Report for the 70 weeks ended 6 April 2025 | E76: https://sustainability.ocadoretail.com/wp-content/uploads/2025/09/Ocado-Sustainability-Report-2024-2025.pdf | F76: 2025 | G76: UK | H76: T1_UK_Specific | I76: Yes | J76: Primary_Evidence | K76: Reduce food waste in our own operations by 20% by 2025 and halve it by 2030 (against a 2022 baseline). | L76: p.52 (Our governance and reporting - Targets) | M76: 24 | N76: waste_reduction_target_20pct | O76: halving_waste_2030 | P76: 2022_baseline | Q76: First_Order | R76: TH_02 | S76: Food_Waste_Prevention | T76: SCOR_Plan | U76: Verified | V76: Cross-checks with EXT_OCA_006 progress metrics | W76: High | X76: Explicit strategic target (20% by 2025, 50% by 2030) drives investment in BD/AI forecasting technologies. Target-driven approach. Addresses RQ3. | Y76: 08-01-2026 | Z76: Include
A77: EXT_OCA_011 | B77: Retailer | C77: Ocado Retail Limited | D77: Annual Report and Financial Statements 2025 | E77: https://ocadoretail.com/wp-content/uploads/2025/09/OCADO-ANNUAL-REPORT_2025.pdf | F77: 2025 | G77: UK | H77: T1_UK_Specific | I77: Yes | J77: Primary_Evidence | K77: In addition to improving our capacity utilisation, we have increased the efficiency of our network with average units per hour (UPH) rising to 225, up 11.9% versus last period (FY24: 201) | L77: p.4 (Chief Executive review) | M77: 28 | N77: UPH_increase_to_225 | O77: OGRP_robotic_pick_rollout | P77: 11.9pct_productivity_increase | Q77: First_Order | R77: TH_01 | S77: Technology_Differentiation | T77: TOE_Tech | U77: Verified | V77: None identified | W77: High | X77: Highlights operational efficiency metrics (UPH, % increase) | Y77: 08-01-2026 | Z77: Include
A78: EXT_SAI_001 | B78: Retailer | C78: J Sainsbury plc | D78: Annual Report and Financial Statements 2025 | E78: https://corporate.sainsburys.co.uk/media/e1lfnybd/sainsbury-annual-report-and-financial-statements-2025.pdf | F78: 2025 | G78: UK | H78: T1_UK_Specific | I78: Yes | J78: Primary_Evidence | K78: We have delivered £230 million of cost savings this year, taking the cumulative total to £1.1 billion since the launch of our Save to Invest programme. This has been driven by end-to-end efficiency programmes including supply chain automation and digitisation. | L78: p.18 (Financial Review - Cost Savings) | M78: 36 | N78: cost_savings_£230m | O78: supply_chain_digitisation | P78: Save_to_Invest_£1.1bn_cumulative | Q78: First_Order | R78: TH_02 | S78: Working_Capital_Improvement | T78: SCOR_Make | U78: Verified | V78: Cross-checks with Save to Invest strategy section | W78: High | X78: CRITICAL: Quantifies financial impact (£230m annual, £1.1bn cumulative) of efficiency programmes. Explicitly links 'supply chain automation and digitisation' to savings, confirming ROI of BD/Tech. Largest quantified BD ROI in dataset. Addresses RQ2. | Y78: 08-01-2026 | Z78: Include
A79: EXT_SAI_002 | B79: Retailer | C79: J Sainsbury plc | D79: Annual Report and Financial Statements 2025 | E79: https://corporate.sainsburys.co.uk/media/e1lfnybd/sainsbury-annual-report-and-financial-statements-2025.pdf | F79: 2025 | G79: UK | H79: T1_UK_Specific | I79: Yes | J79: Primary_Evidence | K79: Nectar360, our loyalty and insights platform, has delivered record profit contribution... Nectar participation in our supermarkets is now over 80%. | L79: p.12 (Strategic Progress - Nectar) | M79: 21 | N79: Nectar_participation_80pct | O79: loyalty_insights_profit | P79: data_monetisation | Q79: First_Order | R79: TH_05 | S79: Technology_Differentiation | T79: 5Vs_Value | U79: Verified | V79: Compare Morrisons More Card 50% (EXT_MOR_002), Lidl Plus 11m (EXT_LID_002) | W79: High | X79: 80% participation indicates massive Volume of customer data. Nectar360 is commercial vehicle for monetising this Value. Highest loyalty participation rate in dataset. Addresses RQ1. | Y79: 08-01-2026 | Z79: Include
A80: EXT_SAI_003 | B80: Retailer | C80: J Sainsbury plc | D80: Annual Report and Financial Statements 2025 | E80: https://corporate.sainsburys.co.uk/media/e1lfnybd/sainsbury-annual-report-and-financial-statements-2025.pdf | F80: 2025 | G80: UK | H80: T1_UK_Specific | I80: Yes | J80: Primary_Evidence | K80: Our food waste reduction programme has achieved a 14% year-on-year reduction in operational waste intensity... supported by the rollout of AI-enabled forecasting tools across fresh categories. | L80: p.34 (Sustainability - Waste) | M80: 26 | N80: waste_intensity_reduction_14pct | O80: AI_forecasting_rollout | P80: fresh_category_focus | Q80: First_Order | R80: TH_01 | S80: Demand_Forecasting | T80: TOE_Tech | U80: Verified | V80: Cross-checks with ESG scorecard | W80: High | X80: CRITICAL: Direct evidence of 'AI-enabled forecasting' (Technology) driving physical reduction in waste (14%). First explicit AI mention for forecasting in dataset. Addresses RQ1 and RQ2. | Y80: 08-01-2026 | Z80: Include
A81: EXT_SAI_004 | B81: Retailer | C81: J Sainsbury plc | D81: Annual Report and Financial Statements 2025 | E81: https://corporate.sainsburys.co.uk/media/e1lfnybd/sainsbury-annual-report-and-financial-statements-2025.pdf | F81: 2025 | G81: UK | H81: T1_UK_Specific | I81: Yes | J81: Primary_Evidence | K81: Capital expenditure increased to £830 million (2024: £786 million), reflecting our accelerated investment in technology infrastructure and automation to drive future efficiencies. | L81: p.52 (Financial Review - Capital Expenditure) | M81: 23 | N81: capex_tech_investment_£830m | O81: automation_infrastructure | P81: future_efficiency_drive | Q81: First_Order | R81: TH_04 | S81: Data_Infrastructure | T81: TOE_Org | U81: Verified | V81: Cross-checks with Cash Flow statement; compare Asda £867m (EXT_ASD_003) | W81: High | X81: Aggregated capex figure (£830m) confirms scale of financial enabler for digital transformation. Tech explicitly named as driver. Compare with Asda Project Future £867m. Addresses RQ3. | Y81: 08-01-2026 | Z81: Include
A82: EXT_SAI_005 | B82: Retailer | C82: J Sainsbury plc | D82: Annual Report and Financial Statements 2025 | E82: https://corporate.sainsburys.co.uk/media/e1lfnybd/sainsbury-annual-report-and-financial-statements-2025.pdf | F82: 2025 | G82: UK | H82: T1_UK_Specific | I82: Yes | J82: Primary_Evidence | K82: Grocery availability improved by 250 basis points year-on-year... driven by improved supplier collaboration and the implementation of our new real-time inventory management system. | L82: p.8 (Chief Executive's Letter) | M82: 24 | N82: availability_improvement_250bps | O82: real_time_inventory_system | P82: supplier_collaboration | Q82: First_Order | R82: TH_01 | S82: Stock_Availability | T82: 5Vs_Velocity | U82: Verified | V82: Compare Morrisons 9% availability improvement (EXT_MOR_001) | W82: High | X82: Hard metric for inventory performance (+250bps availability). Attributes to 'real-time inventory management' (Velocity) and supplier collaboration. Addresses RQ1 and RQ2. | Y82: 08-01-2026 | Z82: Include
A83: EXT_SAI_006 | B83: Retailer | C83: J Sainsbury plc | D83: Plan for Better: Sustainability Report 2025 | E83: https://corporate.sainsburys.co.uk/media/dfkfh1jr/sainsburys-plan-for-better-report-2024-25.pdf | F83: 2025 | G83: UK | H83: T1_UK_Specific | I83: Yes | J83: Primary_Evidence | K83: Responsible Antibiotic Use: Key animal supply chains achieving Sainsbury's responsible use targets for total antibiotic use: All species... 82.0% | L83: p.38 (Animal health and welfare - Performance) | M83: 19 | N83: antibiotic_use_target_achievement_82pct | O83: supply_chain_monitoring | P83: responsible_use_targets | Q83: First_Order | R83: TH_01 | S83: Supply_Chain_Visibility | T83: SCOR_Source | U83: Verified | V83: None identified | W83: High | X83: Demonstrates data monitoring for 'Responsible Antibiotic Use' across entire upstream supply chain (Source phase). Requires aggregation of data from thousands of farmers. Addresses RQ1. | Y83: 08-01-2026 | Z83: Include
A84: EXT_SAI_007 | B84: Retailer | C84: J Sainsbury plc | D84: Plan for Better: Sustainability Report 2025 | E84: https://corporate.sainsburys.co.uk/media/dfkfh1jr/sainsburys-plan-for-better-report-2024-25.pdf | F84: 2025 | G84: UK | H84: T1_UK_Specific | I84: Yes | J84: Primary_Evidence | K84: Critically Important Antibiotic Use: key animal supply chains achieving Sainsbury's responsible use targets for antibiotics deemed critically important for human health (CIAs): All species... 86.7% | L84: p.38 (Animal health and welfare - Performance) | M84: 24 | N84: CIA_reduction_target_86.7pct | O84: critical_health_metrics | P84: human_health_impact | Q84: First_Order | R84: TH_01 | S84: Supply_Chain_Visibility | T84: SCOR_Source | U84: Verified | V84: None identified | W84: High | X84: Specific tracking of 'Critically Important Antibiotics' (CIA) highlights granularity (Variety) of data collected. 86.7% compliance indicates strong but not perfect control. Addresses RQ1. | Y84: 08-01-2026 | Z84: Include
A85: EXT_SAI_008 | B85: Retailer | C85: J Sainsbury plc | D85: Plan for Better: Sustainability Report 2025 | E85: https://corporate.sainsburys.co.uk/media/dfkfh1jr/sainsburys-plan-for-better-report-2024-25.pdf | F85: 2025 | G85: UK | H85: T1_UK_Specific | I85: Yes | J85: Primary_Evidence | K85: Continuous Improvement of Outcome KPIs: animal health and welfare outcome KPIs achieving Sainsbury's KPI performance targets: All species... Physical wellbeing 95.7% (2024) | L85: p.38 (Animal health and welfare - Performance) | M85: 19 | N85: physical_wellbeing_KPI_95.7pct | O85: outcome_KPI_tracking | P85: welfare_performance | Q85: First_Order | R85: TH_01 | S85: Supply_Chain_Visibility | T85: SCOR_Source | U85: Verified | V85: None identified | W85: High | X85: Quantifies 'Physical wellbeing' of livestock using outcome KPIs. Source phase data used to verify ethical standards and product quality. Demonstrates BD in agricultural supply chain. Addresses RQ1. | Y85: 08-01-2026 | Z85: Include
A86: EXT_SAI_009 | B86: Retailer | C86: J Sainsbury plc | D86: Plan for Better: Sustainability Report 2025 | E86: https://corporate.sainsburys.co.uk/media/dfkfh1jr/sainsburys-plan-for-better-report-2024-25.pdf | F86: 2025 | G86: UK | H86: T1_UK_Specific | I86: Yes | J86: Primary_Evidence | K86: Continuous Improvement of Outcome KPIs: animal health and welfare outcome KPIs achieving Sainsbury's KPI performance targets: All species... Mental wellbeing 62.7% (2024) | L86: p.38 (Animal health and welfare - Performance) | M86: 19 | N86: mental_wellbeing_KPI_62.7pct | O86: outcome_KPI_tracking | P86: welfare_performance | Q86: First_Order | R86: TH_01 | S86: Supply_Chain_Visibility | T86: SCOR_Source | U86: Verified | V86: None identified | W86: High | X86: Tracks 'Mental wellbeing' of livestock (62.7%). Ability to capture and quantify such qualitative metric across 'All species' proves advanced data capability in upstream supply chain. Addresses RQ1. | Y86: 08-01-2026 | Z86: Include
... A92: EXT_TES_005 | B92: Retailer | C92: Tesco PLC | D92: Annual Report and Financial Statements 2025 | E92: https://www.tescoplc.com/media/ky0bfwpo/tesco_ar25_interactive.pdf | F92: 2025 | G92: UK | H92: T1_UK_Specific | I92: Yes | J92: Primary_Evidence | K92: Our 'Tesco Marketplace' has expanded... adding over 100,000 new products... leveraging our existing supply chain infrastructure and digital platform to offer more choice. | L92: p.16 (Strategic priorities - Growth) | M92: 24 | N92: Marketplace_SKU_expansion | O92: digital_platform_leverage | P92: supply_chain_integration | Q92: First_Order | R92: TH_01 | S92: Omnichannel_Integration | T92: SCOR_Source | U92: Verified | V92: None identified | W92: High | X92: Shows how digital platforms (Marketplace) allow massive SKU expansion (100k products) without proportionate physical inventory risk. Variety dimension of BD. Addresses RQ1. | Y92: 08-01-2026 | Z92: Include
A93: EXT_TES_006 | B93: Retailer | C93: Tesco PLC | D93: Tesco Sustainability Report 2024/25 | E93: https://www.tescoplc.com/media/wvkj1yic/tesco-sustainability-report-2025.pdf | F93: 2025 | G93: UK | H93: T1_UK_Specific | I93: Yes | J93: Primary_Evidence | K93: In 2024/25, 117 suppliers reported back, the highest number to date, representing over 60% of fresh food sales in the UK. Our data tell us what gets measured gets managed | L93: p.16 (Food Waste - Working with our suppliers) | M93: 31 | N93: supplier_reporting_117_partners | O93: fresh_food_coverage_60pct | P93: measurement_management | Q93: First_Order | R93: TH_04 | S93: Vendor_Partnerships | T93: SCOR_Source | U93: Verified | V93: Compare Morrisons M2030 200 suppliers (EXT_MOR_006) | W93: High | X93: High coverage (60%) of supplier reporting indicates mature Source phase data integration. Essential for Scope 3 visibility and upstream inventory waste management. Addresses RQ1 and RQ3. | Y93: 08-01-2026 | Z93: Exclude | AA93: Supplier sustainability reporting - ESG data collection, not inventory
A94: EXT_TES_007 | B94: Retailer | C94: Tesco PLC | D94: Tesco Sustainability Report 2024/25 | E94: https://www.tescoplc.com/media/wvkj1yic/tesco-sustainability-report-2025.pdf | F94: 2025 | G94: UK | H94: T1_UK_Specific | I94: Yes | J94: Primary_Evidence | K94: Our footprint calculations were mainly based on secondary emissions factors... but we're working towards incorporating primary data... emissions from our milk supply chain now consist of primary data | L94: p.10 (Climate change - Scope 3 methodology) | M94: 30 | N94: primary_data_transition | O94: milk_supply_chain_analytics | P94: secondary_to_primary_shift | Q94: First_Order | R94: TH_03 | S94: Data_Quality_Issues | T94: 5Vs_Veracity | U94: Verified | V94: Compare Morrisons J-curve (EXT_MOR_009), M&S accuracy (EXT_MKS_008) | W94: High | X94: Explicit acknowledgement of shift from 'secondary' (estimated) to 'primary' (measured) data. Improves Veracity. Key evidence of data quality improvement journey. Addresses RQ3. | Y94: 08-01-2026 | Z94: Exclude | AA94: Emissions factors/milk footprint - sustainability accounting, not inventory
A95: EXT_TES_008 | B95: Retailer | C95: Tesco PLC | D95: Tesco Sustainability Report 2024/25 | E95: https://www.tescoplc.com/media/wvkj1yic/tesco-sustainability-report-2025.pdf | F95: 2025 | G95: UK | H95: T1_UK_Specific | I95: Yes | J95: Primary_Evidence | K95: We have developed an AI governance framework to ensure that any AI technologies utilised by the business are implemented are fair, safe, transparent, explainable, accountable and sustainable | L95: p.57 (SASB content index - Data security) | M95: 28 | N95: AI_governance_framework | O95: fair_safe_transparent | P95: accountable_sustainable | Q95: Second_Order | R95: TH_03 | S95: Data_Governance | T95: TOE_Org | U95: Verified | V95: None identified | W95: High | X95: CRITICAL: Only extract mentioning formal 'AI Governance Framework'. Addresses black-box risk by mandating 'explainable' AI. Key organizational enabler/barrier removal. Addresses RQ3. | Y95: 08-01-2026 | Z95: Include
A96: EXT_TES_009 | B96: Retailer | C96: Tesco PLC | D96: Tesco Sustainability Report 2024/25 | E96: https://www.tescoplc.com/media/wvkj1yic/tesco-sustainability-report-2025.pdf | F96: 2025 | G96: UK | H96: T1_UK_Specific | I96: Yes | J96: Primary_Evidence | K96: 82% of unsold food safe for human consumption in the UK redistributed to humans or animals... (14)% percentage change in tonnes of food wasted... compared to baseline | L96: p.47 (Databook - Food waste) | M96: 26 | N96: waste_redistribution_82pct | O96: waste_reduction_14pct | P96: UK_redistribution | Q96: First_Order | R96: TH_02 | S96: Food_Waste_Prevention | T96: SCOR_Return | U96: Verified | V96: Cross-checks with Annual Report waste metrics | W96: High | X96: Hard metrics for Return phase. 82% redistribution rate is direct outcome of inventory management systems identifying surplus. 14% reduction vs baseline. Addresses RQ2. | Y96: 08-01-2026 | Z96: Include
A97: EXT_TES_010 | B97: Retailer | C97: Tesco PLC | D97: Tesco Sustainability Report 2024/25 | E97: https://www.tescoplc.com/media/wvkj1yic/tesco-sustainability-report-2025.pdf | F97: 2025 | G97: UK | H97: T1_UK_Specific | I97: Yes | J97: Primary_Evidence | K97: The latest 'Tesco train' can move 600,000 cases each week... Across our network, 85% of all outbound goods from Daventry Distribution Centre are moved by rail | L97: p.11 (Climate change - Transport) | M97: 25 | N97: rail_freight_600k_cases | O97: Daventry_outbound_85pct | P97: modal_shift_efficiency | Q97: First_Order | R97: TH_01 | S97: Supply_Chain_Visibility | T97: SCOR_Deliver | U97: Verified | V97: None identified | W97: High | X97: Quantifies logistics volume (600k cases/week) managed via rail. Requires precise scheduling data (Velocity) to integrate with DC operations. Primary cost benefit is transport efficiency. Addresses RQ1. | Y97: 08-01-2026 | Z97: Include
A98: EXT_WAI_001 | B98: Retailer | C98: John Lewis plc (Waitrose) | D98: Annual Report and Accounts 2025 | E98: https://find-and-update.company-information.service.gov.uk/company/00233462/filing-history | F98: 2025 | G98: UK | H98: T1_UK_Specific | I98: Yes | J98: Primary_Evidence | K98: Availability was strong at 96.5%... supported by our focus on simpler, more efficient processes and investment in supply chain technology. | L98: p.8 (Waitrose Trading Review) | M98: 22 | N98: availability_96.5pct | O98: supply_chain_tech_investment | P98: process_simplification | Q98: First_Order | R98: TH_01 | S98: Stock_Availability | T98: 5Vs_Velocity | U98: Verified | V98: None identified | W98: High | X98: Quantifies Availability (96.5%) as key output of 'supply chain technology'. Directly links tech investment to operational performance. Highest availability figure in dataset. Addresses RQ1. | Y98: 08-01-2026 | Z98: Include
A99: EXT_WAI_002 | B99: Retailer | C99: John Lewis plc (Waitrose) | D99: Annual Report and Accounts 2025 | E99: https://find-and-update.company-information.service.gov.uk/company/00233462/filing-history | F99: 2025 | G99: UK | H99: T1_UK_Specific | I99: Yes | J99: Primary_Evidence | K99: Waitrose wastage was reduced by 10% year-on-year, driven by improved forecasting accuracy and our 'waste less, save more' initiatives. | L99: p.9 (Waitrose Trading Review) | M99: 21 | N99: waste_reduction_10pct | O99: forecasting_accuracy | P99: waste_less_save_more | Q99: First_Order | R99: TH_02 | S99: Food_Waste_Prevention | T99: SCOR_Plan | U99: Verified | V99: Cross-checks with ESG section | W99: High | X99: Direct evidence of 'improved forecasting' (Analytics) driving 10% reduction in physical waste. Clear BD-outcome link. Addresses RQ2. | Y99: 08-01-2026 | Z99: Include
A100: EXT_WAI_003 | B100: Retailer | C100: John Lewis plc (Waitrose) | D100: Annual Report and Accounts 2025 | E100: https://find-and-update.company-information.service.gov.uk/company/00233462/filing-history | F100: 2025 | G100: UK | H100: T1_UK_Specific | I100: Yes | J100: Primary_Evidence | K100: We have invested £112m in technology this year, including the early stages of a new ERP system to replace legacy infrastructure and improve data visibility across the Partnership. | L100: p.14 (Financial Review - Capital Investment) | M100: 29 | N100: tech_investment_£112m | O100: ERP_replacement | P100: legacy_infrastructure_barrier | Q100: Mixed | R100: TH_04 | S100: Data_Infrastructure | T100: TOE_Tech | U100: Verified | V100: Cross-checks with Cash Flow statement | W100: High | X100: Explicitly names 'legacy infrastructure' as something being replaced. Cost (£112m) and goal ('data visibility') highlight barrier/enabler dynamic. Compare M&S legacy admission. Addresses RQ3. | Y100: 08-01-2026 | Z100: Include
A101: EXT_WAI_004 | B101: Retailer | C101: John Lewis plc (Waitrose) | D101: Annual Report and Accounts 2025 | E101: https://find-and-update.company-information.service.gov.uk/company/00233462/filing-history | F101: 2025 | G101: UK | H101: T1_UK_Specific | I101: Yes | J101: Primary_Evidence | K101: Our partnership with Uber Eats has expanded to over 200 stores, leveraging real-time inventory data to offer customers delivery in as little as 20 minutes. | L101: p.8 (Waitrose Trading Review - Online) | M101: 26 | N101: Uber_Eats_200_stores | O101: real_time_inventory_data | P101: rapid_delivery_scaling | Q101: First_Order | R101: TH_01 | S101: Omnichannel_Integration | T101: TOE_Org | U101: Verified | V101: None identified | W101: High | X101: Demonstrates 'real-time inventory data' (Velocity) enabling new commercial channels (Uber Eats). 200 stores shows maturity. 20-minute delivery requires precise stock visibility. Addresses RQ1. | Y101: 08-01-2026 | Z101: Include
A102: EXT_WAI_005 | B102: Retailer | C102: John Lewis plc (Waitrose) | D102: Annual Report and Accounts 2025 | E102: https://find-and-update.company-information.service.gov.uk/company/00233462/filing-history | F102: 2025 | G102: UK | H102: T1_UK_Specific | I102: Yes | J102: Primary_Evidence | K102: Partnership operational cash flow improved by £180m, partly due to tighter working capital management and a reduction in stock holding days. | L102: p.16 (Financial Review - Cash Flow) | M102: 24 | N102: stock_holding_reduction | O102: working_capital_improvement | P102: cash_flow_impact | Q102: First_Order | R102: TH_02 | S102: Working_Capital_Improvement | T102: SCOR_Source | U102: Verified | V102: Cross-checks with Balance Sheet | W102: High | X102: Links inventory metrics ('stock holding days') to financial health (£180m cash flow). Proof of Value (5Vs) of tighter inventory management. Addresses RQ2. | Y102: 08-01-2026 | Z102: Include
A103: EXT_WAI_006 | B103: Retailer | C103: John Lewis Partnership (Waitrose) | D103: Ethics & Sustainability Report 2024/25 | E103: https://www.johnlewispartnership.co.uk/~/media/Files/J/john-lewis/corp/documents/jlp-es-report-2024-25.pdf | F103: 2025 | G103: UK | H103: T1_UK_Specific | I103: Yes | J103: Primary_Evidence | K103: In collaboration with Land App, Waitrose is supporting 2,500 of its own-brand UK farms to map current habitats. We're also seeking to develop land management plans for these farms | L103: p.14 (Nature & Biodiversity - Mapping habitat) | M103: 27 | N103: digital_mapping_2500_farms | O103: Land_App_collaboration | P103: habitat_data_collection | Q103: First_Order | R103: TH_04 | S103: Data_Infrastructure | T103: SCOR_Source | U103: Verified | V103: Compare Morrisons Map of Ag (EXT_MOR_008), Asda Land App (EXT_ASD_008) | W103: High | X103: Explicit use of digital tool ('Land App') to capture data from 2,500 suppliers (Volume/Variety). Demonstrates Source phase data integration. Compare with Morrisons Map of Ag and Asda Land App trial. Addresses RQ1. | Y103: 08-01-2026 | Z103: Include
A104: EXT_WAI_007 | B104: Retailer | C104: John Lewis Partnership (Waitrose) | D104: Ethics & Sustainability Report 2024/25 | E104: https://www.johnlewispartnership.co.uk/~/media/Files/J/john-lewis/corp/documents/jlp-es-report-2024-25.pdf | F104: 2025 | G104: UK | H104: T1_UK_Specific | I104: Yes | J104: Primary_Evidence | K104: In collaboration with our own-brand pasta supplier, Daybreak Foods... Waitrose has begun diverting up to 130 tonnes of surplus pasta a year to FareShare. | L104: p.13 (Circularity & Waste - Food waste) | M104: 25 | N104: surplus_diversion_130t | O104: supplier_collaboration_Daybreak | P104: waste_redistribution_FareShare | Q104: First_Order | R104: TH_02 | S104: Food_Waste_Prevention | T104: SCOR_Return | U104: Verified | V104: Cross-checks with Community section | W104: High | X104: Quantifies specific Return phase intervention (130t diverted). Shows how supply chain collaboration (Daybreak) reduces physical inventory waste. Addresses RQ2. | Y104: 08-01-2026 | Z104: Include
A105: EXT_WAI_008 | B105: Retailer | C105: John Lewis Partnership | D105: Ethics & Sustainability Report 2024/25 | E105: https://www.johnlewispartnership.co.uk/~/media/Files/J/john-lewis/corp/documents/jlp-es-report-2024-25.pdf | F105: 2025 | G105: UK | H105: T1_UK_Specific | I105: Yes | J105: Primary_Evidence | K105: We reduced transport carbon emissions by 50% compared to 2018... put an additional 43 biomethane trucks on the road... and operated 65 trucks that self-generate electricity | L105: p.15 (Climate Action - Fleet decarbonisation) | M105: 32 | N105: transport_emissions_reduction_50pct | O105: biomethane_trucks_43 | P105: fleet_telemetry_data | Q105: First_Order | R105: TH_02 | S105: Transport_Efficiency | T105: SCOR_Deliver | U105: Verified | V105: Cross-checks with Fleet data | W105: High | X105: Strong metric (50% reduction) driven by fleet innovation. Requires precise logistics data to manage mixed fleets (biomethane/electric) efficiently. Primary benefit is transport cost reduction. Addresses RQ2. | Y105: 08-01-2026 | Z105: Exclude | AA105: Transport carbon emissions - sustainability, not inventory optimisation
...

Sheet Thematic_Codebook
A1: THEMATIC CODEBOOK - Version 2.1 (6 Themes)
A3: Theme_ID | B3: Theme_Name | C3: Description | D3: Sub_Themes | E3: Primary_RQ | F3: Extract_Count
A4: TH_01 | B4: BD_Operational_Efficiency | C4: Measurable operational improvements from BD/AI implementation | D4: Demand_Forecasting; Inventory_Accuracy; Stock_Availability; Labour_Optimisation; Supply_Chain_Visibility; Omnichannel_Integration; ROI_Metrics; Network_Efficiency | E4: RQ1 | F4: =COUNTIF(Extraction_Log!R:R,A4) -> 88
A5: TH_02 | B5: BD_Cost_Reduction | C5: Quantifiable cost savings, financial benefits, and waste reduction | D5: Food_Waste_Prevention; Markdown_Optimisation; Transport_Efficiency; Energy_Optimisation; Shrinkage_Reduction; Working_Capital_Improvement | E5: RQ2 | F5: =COUNTIF(Extraction_Log!R:R,A5) -> 56
A6: TH_03 | B6: Adoption_Barriers | C6: Factors impeding or slowing BD/AI implementation | D6: Technical_Complexity; Skills_Gap; Legacy_Systems; Implementation_Cost; Data_Quality_Issues; Data_Governance; Change_Resistance; Integration_Challenges | E6: RQ3 | F6: =COUNTIF(Extraction_Log!R:R,A6) -> 49
A7: TH_04 | B7: Implementation_Enablers | C7: Factors facilitating successful BD/AI adoption | D7: Leadership_Support; Vendor_Partnerships; Data_Infrastructure; Cloud_Adoption; Talent_Development; Scalable_Architecture; Centre_of_Excellence; Pilot_Programme_Success | E7: RQ3 | F7: =COUNTIF(Extraction_Log!R:R,A7) -> 51
A8: TH_05 | B8: Competitive_Dynamics | C8: How BD/AI affects competitive positioning and market structure | D8: Market_Concentration; Discounter_Pressure; Online_Competition; Technology_Differentiation; First_Mover_Advantage; Capability_Gap | E8: RQ1, RQ3 | F8: =COUNTIF(Extraction_Log!R:R,A8) -> 28
A9: TH_06 | B9: UK_Market_Context | C9: UK-specific market conditions affecting BD adoption | D9: Regulatory_Environment; Labour_Market; Consumer_Behaviour; Brexit_Impact; Inflation_Pressure; Channel_Dynamics | E9: RQ1, RQ2, RQ3 | F9: =COUNTIF(Extraction_Log!R:R,A9) -> 31

Sheet Geographic_Tiering
A1: GEOGRAPHIC TIERING FRAMEWORK
A3: Tier | B3: Code | C3: Criteria | D3: Citation Framing | E3: Usage
A4: Tier 1 | B4: T1_UK_Specific | C4: UK retailers named; UK market data; UK government sources | D4: "In the UK context..." | E4: Primary_Evidence
A5: Tier 2 | B5: T2_UK_Applicable | C5: European studies with UK explicitly in sample | D5: "European research including UK shows..." | E5: Supporting_Evidence
A6: Tier 3 | B6: T3_Transferable | C6: US/Global studies on comparable retail contexts | D6: "International evidence suggests..." | E6: Comparative
A7: Tier 4 | B7: T4_Conceptual | C7: Theoretical frameworks; methodology studies | D7: "The framework proposed by..." | E7: Conceptual_Only

Sheet Validation_Tracker
A1: VALIDATION TRACKER - UKRIO Research Integrity
A3: Claim | B3: Primary_Source | C3: Confirming_Source | D3: Status | E3: Discrepancy_Notes | F3: Resolution
A4: 72% operational food waste reduction (2017-2024) | B4: EXT_ALD_002 (Sustainability Report) | C4: EXT_ALD_009 (Financial - 67% to 2023) | D4: Verified | E4: 67% to 2023, then 72% by 2024 - consistent progression | F4: Both figures valid; cite 72% as latest with 67% as trajectory
A5: £19.775m D&A Services spend (2024) | B5: EXT_ALD_006 (Financial Statements) | C5: Single source (KPMG audited) | D5: Verified | E5: No independent confirmation available | F5: Use as primary evidence; note audited status
A6: 625 water AMR devices installed | B6: EXT_ALD_004 (Sustainability Report) | C6: EXT_ALD_010 (Financial - 595 AMS) | D6: Cross_Check_Required | E6: Sustainability=625 AMR, Financial=595 AMS | F6: Clarify: AMR vs AMS terminology; possible different measurement periods
A7: IRFM predictive monitoring system | B7: EXT_ALD_007 (Financial Statements) | C7: Single source | D7: Verified | E7: Specific middleware named | F7: Strong evidence of BD technology deployment
A8: £599m investing activities incl. tech | B8: EXT_ALD_008 (Financial Statements) | C8: KPMG audited | D8: Verified | E8: Aggregated figure (tech + stores + distribution) | F8: Use cautiously; tech portion not isolated
A9: £867m Project Future IT transformation cost | B9: EXT_ASD_003 (Financial Statements) | C9: Cross-checks with Capital Expenditure p.15 | D9: Verified | E9: Single source but audited; no independent confirmation | F9: Use as primary evidence for transformation scale
A10: Inventory loss reduction £140.2m to £87.1m (38%) | B10: EXT_ASD_004 (Financial Statements) | C10: Correlates with EXT_ASD_002 (inventory solutions rollout) | D10: Verified | E10: Timing aligns with 800-store inventory system rollout | F10: Strong evidence of BD impact on shrinkage
A11: 15.1% YoY food waste reduction | B11: EXT_ASD_009 (ESG Report) | C11: Cross-checks with Zero Waste section p.12 | D11: Verified | E11: Single year metric; compare with Aldi's longitudinal data | F11: Use alongside Aldi's 72% (2017-2024) for comparison
A12: Shelf life extension 9 days (packaging) | B12: EXT_ASD_007 (ESG Report) | C12: Compare with EXT_ALD_003 (Aldi 7 days) | D12: Verified | E12: Similar approach across retailers | F12: Evidence of industry-wide inventory optimisation trend
A13: 800 stores inventory management solutions | B13: EXT_ASD_002 (Financial Statements) | C13: Links to EXT_ASD_001 (Project Future) | D13: Verified | E13: Primarily small formats; scale for large stores unclear | F13: Note format limitation in analysis
A14: 38% food waste reduction (FY18-FY25) | B14: EXT_ICE_003 (Financial Statements) | C14: EXT_ICE_008 (Sustainability Report) | D14: Verified | E14: Both sources report identical 38% figure; 12% YoY consistent | F14: Strong cross-validated evidence
... A99: 1/3 companies at survival risk | B99: EXT_ACC_011 (Accenture) | C99: Cross-checks with Marsh | D99: Verified | E99: Existential threat | F99: Maturity <25%

Sheet Summary_Statistics
A1: EXTRACTION SUMMARY STATISTICS
A3: Metric | B3: Count
A4: Total Extracts | B4: 302
A6: BY GEOGRAPHIC TIER
A7: T1_UK_Specific | B7: =COUNTIF(Extraction_Log!H:H,"T1_UK_Specific") -> 196
A8: T2_UK_Applicable | B8: =COUNTIF(Extraction_Log!H:H,"T2_UK_Applicable") -> 12
A9: T3_Transferable | B9: =COUNTIF(Extraction_Log!H:H,"T3_Transferable") -> 80
A10: T4_Conceptual | B10: =COUNTIF(Extraction_Log!H:H,"T4_Conceptual") -> 3
A12: BY THEME
A13: TH_01 (BD_Operational_Efficiency) | B13: =COUNTIF(Extraction_Log!R:R,"TH_01") -> 88
A14: TH_02 (BD_Cost_Reduction) | B14: =COUNTIF(Extraction_Log!R:R,"TH_02") -> 56
A15: TH_03 (Adoption_Barriers) | B15: =COUNTIF(Extraction_Log!R:R,"TH_03") -> 49
A16: TH_04 (Implementation_Enablers) | B16: =COUNTIF(Extraction_Log!R:R,"TH_04") -> 51
A17: TH_05 (Competitive_Dynamics) | B17: =COUNTIF(Extraction_Log!R:R,"TH_05") -> 28
A18: TH_06 (UK_Market_Context) | B18: =COUNTIF(Extraction_Log!R:R,"TH_06") -> 31
A20: BY CONFIDENCE LEVEL
A21: High | B21: =COUNTIF(Extraction_Log!W:W,"High") -> 259
A22: Medium | B22: =COUNTIF(Extraction_Log!W:W,"Medium") -> 43
A23: Low | B23: =COUNTIF(Extraction_Log!W:W,"Low") -> 1
A25: BY FRAMEWORK ALIGNMENT
A26: TOE_Tech | B26: =COUNTIF(Extraction_Log!T:T,"TOE_Tech") -> 44
A27: TOE_Org | B27: =COUNTIF(Extraction_Log!T:T,"TOE_Org") -> 36
A28: TOE_Env | B28: =COUNTIF(Extraction_Log!T:T,"TOE_Env") -> 56
A29: SCOR_Plan | B29: =COUNTIF(Extraction_Log!T:T,"SCOR_Plan") -> 17
A30: SCOR_Source | B30: =COUNTIF(Extraction_Log!T:T,"SCOR_Source") -> 23
A31: SCOR_Make | B31: =COUNTIF(Extraction_Log!T:T,"SCOR_Make") -> 8
A32: SCOR_Deliver | B32: =COUNTIF(Extraction_Log!T:T,"SCOR_Deliver") -> 13
A33: SCOR_Return | B33: =COUNTIF(Extraction_Log!T:T,"SCOR_Return") -> 25
A34: 5Vs_Volume | B34: =COUNTIF(Extraction_Log!T:T,"5Vs_Volume") -> 8
A35: 5Vs_Velocity | B35: =COUNTIF(Extraction_Log!T:T,"5Vs_Velocity") -> 12
A36: 5Vs_Variety | B36: =COUNTIF(Extraction_Log!T:T,"5Vs_Variety") -> 8
A37: 5Vs_Veracity | B37: =COUNTIF(Extraction_Log!T:T,"5Vs_Veracity") -> 18
A38: 5Vs_Value | B38: =COUNTIF(Extraction_Log!T:T,"5Vs_Value") -> 35
A39: Multiple | B39: =COUNTIF(Extraction_Log!T:T,"Multiple") -> 0
A41: BY CONFIRMATION STATUS
A42: Verified | B42: =COUNTIF(Extraction_Log!U:U,"Verified") -> 302
A43: Pending | B43: =COUNTIF(Extraction_Log!U:U,"Pending") -> 0
A44: Cross_Check_Required | B44: =COUNTIF(Extraction_Log!U:U,"Cross_Check_Required") -> 1
A45: Contradicted | B45: =COUNTIF(Extraction_Log!U:U,"Contradicted") -> 0

Sheet Dropdown_Reference
A1: DROPDOWN VALIDATION REFERENCE
A3: Column | B3: Field | C3: Valid Values
A4: B | B4: Source_Type | C4: Consultancy, Trade_Association, Government, Academic, Retailer, Vendor, News
A5: G | B5: Geo_Scope | C5: UK, Europe, US, Global, Multiple
A6: H | B6: Geo_Tier | C6: T1_UK_Specific, T2_UK_Applicable, T3_Transferable, T4_Conceptual
A7: I | B7: UK_Data | C7: Yes, No, Partial, Unknown
A8: J | B8: Geo_Usage | C8: Primary_Evidence, Supporting_Evidence, Comparative, Conceptual_Only
A9: Q | B9: Coding_Level | C9: First_Order, Second_Order, Mixed
A10: R | B10: Theme_Candidate | C10: TH_01, TH_02, TH_03, TH_04, TH_05, TH_06
A11: T | B11: Framework_Alignment | C11: TOE_Tech, TOE_Org, TOE_Env, SCOR_Plan, SCOR_Source, SCOR_Make, SCOR_Deliver, SCOR_Return, 5Vs_Volume, 5Vs_Velocity, 5Vs_Variety, 5Vs_Veracity, 5Vs_Value, Multiple, None
A12: U | B12: Confirmation_Status | C12: Verified, Pending, Cross_Check_Required, Rejected, Contradicted
A13: W | B13: Confidence_Level | C13: High, Medium, Low
A14: Z | B14: Reviewer_Decision | C14: Include, Exclude, Merge, Refine, Flagged

Sheet Sheet1
A1: everyone to fight food waste together. The Too Good To Go app is the world's largest marketplace for surplus food, and through it we sell our unsold food in 'Surprise Bags' for local users to collect in store. We have saved over 1 million Surprise Bags from going to waste since 2023 - an equivalent of more than 5,000 tonnes of food, and saved our customers over £9 million.
